examples/lua/alu/alu.v
module alu(
	input signed [31:0] data_a,
	input signed [31:0] data_b,
	input [31:0] select,
	output signed [31:0] result_y
);
	wire signed [31:0] A;
	wire signed [31:0] B;
	reg signed [31:0] Y;
	assign result_y = Y;
	assign A = data_a;
	assign B = data_b;
	always @(*) begin
		case (select[3:0])
			4'b0000: begin
				Y <= A + B;
			end
			4'b0001: begin
				Y <= A - B;
			end
			4'b0010: begin
				Y <= A * B;
			end
			4'b0011: begin
				Y <= A / B;
			end
			4'b0100: begin
				Y <= A % B;
			end
			4'b0101: begin
				Y <= B;
			end
			4'b0110: begin
				Y <= A ** B;
			end
			4'b0111: begin
				Y <= -A;
			end
			4'b1000: begin
				Y <= A | B;
			end
			4'b1001: begin
				Y <= A & B;
			end
			4'b1010: begin
				Y <= A ^ B;
			end
			4'b1011: begin
				Y <= A > B;
			end
			4'b1100: begin
				Y <= A == B;
			end
			4'b1101: begin
				Y <= A <<< B[4:0];
			end
			4'b1110: begin
				Y <= A >>> B[4:0];
			end
			4'b1111: begin
				Y <= A;
			end
		endcase
	end
endmodule

examples/lua/alu/alu_testbench.v
`include "alu.v"

module tb;
	reg signed [31:0] data_a;
	reg signed [31:0] data_b;
	reg [31:0] select;
	wire signed [31:0] result_y;

	alu dut (
		.data_a(data_a),
		.data_b(data_b),
		.select(select),
		.result_y(result_y)
	);

	integer i;
	integer op_select;
	integer seed;
	initial begin
		seed = 123;
		$dumpfile("alu_testbench.vcd");
		$dumpvars(1, tb);

		for (i = 0; i < 50; i = i + 1) begin
			data_a = $random(seed);
			data_b = $random(seed);

			for (op_select = 0; op_select < 16; op_select = op_select + 1) begin
				select = op_select;
				#1;
			end
		end
		$finish;
	end
endmodule

examples/lua/alu/alu_testbench.vcd
$date
	Fri Oct 10 01:56:59 2025
$end
$version
	Icarus Verilog
$end
$timescale
	1s
$end
$scope module tb $end
$var wire 32 ! result_y [31:0] $end
$var reg 32 " data_a [31:0] $end
$var reg 32 # data_b [31:0] $end
$var reg 32 $ select [31:0] $end
$var integer 32 % i [31:0] $end
$var integer 32 & op_select [31:0] $end
$var integer 32 ' seed [31:0] $end
$upscope $end
$enddefinitions $end
$comment Show the parameter values. $end
$dumpall
$end
#0
$dumpvars
b10011110100000011101001110000001 '
b0 &
b0 %
b0 $
b11110100000011101010100111101 #
b10000000100000011010001000000001 "
b10011111000000110111011100111110 !
$end
#1
b1100001111111111100110011000100 !
b1 $
b1 &
#2
b111011001011110110111100111101 !
b10 $
b10 &
#3
b11111111111111111111111111111100 !
b11 $
b11 &
#4
b11111010100010001111011011110101 !
b100 $
b100 &
#5
b11110100000011101010100111101 !
b101 $
b101 &
#6
b1010010010001011001101000000001 !
b110 $
b110 &
#7
b1111111011111100101110111111111 !
b111 $
b111 &
#8
b10011110100000011111011100111101 !
b1000 $
b1000 &
#9
b100000011000000000000001 !
b1001 $
b1001 &
#10
b10011110000000000111011100111100 !
b1010 $
b1010 &
#11
b0 !
b1011 $
b1011 &
#12
b1100 $
b1100 &
#13
b100000000000000000000000000000 !
b1101 $
b1101 &
#14
b11111111111111111111111111111100 !
b1110 $
b1110 &
#15
b10000000100000011010001000000001 !
b1111 $
b1111 &
#16
b1100011110101100101000011000111 !
b0 $
b10001010101000010110010000010101 #
b11011001001101001110110010110010 "
b1010101000010110001101110111 '
b1 %
b0 &
#17
b1001110100100111000100010011101 !
b1 $
b1 &
#18
b1001101101111101111001010011010 !
b10 $
b10 &
#19
b0 !
b11 $
b11 &
#20
b11011001001101001110110010110010 !
b100 $
b100 &
#21
b10001010101000010110010000010101 !
b101 $
b101 &
#22
b0 !
b110 $
b110 &
#23
b100110110010110001001101001110 !
b111 $
b111 &
#24
b11011011101101011110110010110111 !
b1000 $
b1000 &
#25
b10001000001000000110010000010000 !
b1001 $
b1001 &
#26
b1010011100101011000100010100111 !
b1010 $
b1010 &
#27
b1 !
b1011 $
b1011 &
#28
b0 !
b1100 $
b1100 &
#29
b10010110010000000000000000000000 !
b1101 $
b1101 &
#30
b11111111111111111111111011001001 !
b1110 $
b1110 &
#31
b11011001001101001110110010110010 !
b1111 $
b1111 &
#32
b1100101010110111000100011001010 !
b0 $
b11001100100110101101011010011001 #
b10011000110000001011001000110001 "
b1001100100110101101010111011101 '
b10 %
b0 &
#33
b11001100001001011101101110011000 !
b1 $
b1 &
#34
b10011101100110010111010101001001 !
b10 $
b10 &
#35
b10 !
b11 $
b11 &
#36
b11111111100010110000010011111111 !
b100 $
b100 &
#37
b11001100100110101101011010011001 !
b101 $
b101 &
#38
b0 !
b110 $
b110 &
#39
b1100111001111110100110111001111 !
b111 $
b111 &
#40
b11011100110110101111011010111001 !
b1000 $
b1000 &
#41
b10001000100000001001001000010001 !
b1001 $
b1001 &
#42
b1010100010110100110010010101000 !
b1010 $
b1010 &
#43
b0 !
b1011 $
b1011 &
#44
b1100 $
b1100 &
#45
b1100010000000000000000000000000 !
b1101 $
b1101 &
#46
b11111111111111111111111111001100 !
b1110 $
b1110 &
#47
b10011000110000001011001000110001 !
b1111 $
b1111 &
#48
b1011110000011111010101010111011 !
b0 $
b11010011010110010010111010100110 #
b10001010101101100111110000010101 "
b1010011010110010010110000110011 '
b11 %
b0 &
#49
b10110111010111010100110101101111 !
b1 $
b1 &
#50
b101110111011010011101110011110 !
b10 $
b10 &
#51
b10 !
b11 $
b11 &
#52
b11100100000001000001111011001001 !
b100 $
b100 &
#53
b11010011010110010010111010100110 !
b101 $
b101 &
#54
b0 !
b110 $
b110 &
#55
b1110101010010011000001111101011 !
b111 $
b111 &
#56
b11011011111111110111111010110111 !
b1000 $
b1000 &
#57
b10000010000100000010110000000100 !
b1001 $
b1001 &
#58
b1011001111011110101001010110011 !
b1010 $
b1010 &
#59
b0 !
b1011 $
b1011 &
#60
b1100 $
b1100 &
#61
b10101101100111110000010101000000 !
b1101 $
b1101 &
#62
b11111110001010101101100111110000 !
b1110 $
b1110 &
#63
b10001010101101100111110000010101 !
b1111 $
b1111 &
#64
b10101011000010101010000101010101 !
b0 $
b10111001001100001010010001110010 #
b11110001110110011111110011100011 "
b111001001100001010001111111001 '
b100 %
b0 &
#65
b111000101010010101100001110001 !
b1 $
b1 &
#66
b11001110101001000000100100010110 !
b10 $
b10 &
#67
b0 !
b11 $
b11 &
#68
b11110001110110011111110011100011 !
b100 $
b100 &
#69
b10111001001100001010010001110010 !
b101 $
b101 &
#70
b0 !
b110 $
b110 &
#71
b1110001001100000001100011101 !
b111 $
b111 &
#72
b11111001111110011111110011110011 !
b1000 $
b1000 &
#73
b10110001000100001010010001100010 !
b1001 $
b1001 &
#74
b1001000111010010101100010010001 !
b1010 $
b1010 &
#75
b1 !
b1011 $
b1011 &
#76
b0 !
b1100 $
b1100 &
#77
b11110011100011000000000000000000 !
b1101 $
b1101 &
#78
b11111111111111111111110001110110 !
b1110 $
b1110 &
#79
b11110001110110011111110011100011 !
b1111 $
b1111 &
#80
b10110001110000000111000101011 !
b0 $
b10101101111110000001100001011011 #
b1101000001111111111010111010000 "
b101101111110000001011010101111 '
b101 %
b0 &
#81
b10111010010001111101110101110101 !
b1 $
b1 &
#82
b10111111010001111110000011110000 !
b10 $
b10 &
#83
b11111111111111111111111111111111 !
b11 $
b11 &
#84
b10110001110000000111000101011 !
b100 $
b100 &
#85
b10101101111110000001100001011011 !
b101 $
b101 &
#86
b0 !
b110 $
b110 &
#87
b10010111110000000000101000110000 !
b111 $
b111 &
#88
b11101101111111111111110111011011 !
b1000 $
b1000 &
#89
b101000001110000001000001010000 !
b1001 $
b1001 &
#90
b11000101110001111110110110001011 !
b1010 $
b1010 &
#91
b1 !
b1011 $
b1011 &
#92
b0 !
b1100 $
b1100 &
#93
b10000000000000000000000000000000 !
b1101 $
b1101 &
#94
b1101 !
b1110 $
b1110 &
#95
b1101000001111111111010111010000 !
b1111 $
b1111 &
#96
b100110110110010110101001001101 !
b0 $
b100111010110010101101101001110 #
b11111111100000000000111011111111 "
b10100111010110010101100111010101 '
b110 %
b0 &
#97
b11011000001001101011001110110001 !
b1 $
b1 &
#98
b1101110000000000011011010110010 !
b10 $
b10 &
#99
b0 !
b11 $
b11 &
#100
b11111111100000000000111011111111 !
b100 $
b100 &
#101
b100111010110010101101101001110 !
b101 $
b101 &
#102
b100010100000010110111000000001 !
b110 $
b110 &
#103
b11111111111000100000001 !
b111 $
b111 &
#104
b11111111110110010101111111111111 !
b1000 $
b1000 &
#105
b100111000000000000101001001110 !
b1001 $
b1001 &
#106
b11011000110110010101010110110001 !
b1010 $
b1010 &
#107
b0 !
b1011 $
b1011 &
#108
b1100 $
b1100 &
#109
b11101111111100000000000000 !
b1101 $
b1101 &
#110
b11111111111111111111111000000000 !
b1110 $
b1110 &
#111
b11111111100000000000111011111111 !
b1111 $
b1111 &
#112
b1111111000100110010000011110 !
b0 $
b10101001111100001010000001010011 #
b1100101111100011100001111001011 "
b101001111100001001111011101011 '
b111 %
b0 &
#113
b10111100000000010010001101111000 !
b1 $
b1 &
#114
b10111001000100010101101011010001 !
b10 $
b10 &
#115
b11111111111111111111111111111111 !
b11 $
b11 &
#116
b1111111000100110010000011110 !
b100 $
b100 &
#117
b10101001111100001010000001010011 !
b101 $
b101 &
#118
b0 !
b110 $
b110 &
#119
b10011010000011100011110000110101 !
b111 $
b111 &
#120
b11101101111100011110001111011011 !
b1000 $
b1000 &
#121
b100001111100001000000001000011 !
b1001 $
b1001 &
#122
b11001100000000010110001110011000 !
b1010 $
b1010 &
#123
b1 !
b1011 $
b1011 &
#124
b0 !
b1100 $
b1100 &
#125
b11110010110000000000000000000 !
b1101 $
b1101 &
#126
b110010111110 !
b1110 $
b1110 &
#127
b1100101111100011100001111001011 !
b1111 $
b1111 &
#128
b1100010001111110000100011000100 !
b0 $
b1110101100100101101010111101011 #
b11101100101011000011001011011001 "
b11110101100100101101001101110001 '
b1000 %
b0 &
#129
b1110111000110010101110011101110 !
b1 $
b1 &
#130
b10110101001000110011101000110011 !
b10 $
b10 &
#131
b0 !
b11 $
b11 &
#132
b11101100101011000011001011011001 !
b100 $
b100 &
#133
b1110101100100101101010111101011 !
b101 $
b101 &
#134
b11111001111010110001011000001001 !
b110 $
b110 &
#135
b10011010100111100110100100111 !
b111 $
b111 &
#136
b11111101101111101111011111111011 !
b1000 $
b1000 &
#137
b1100100100000000001000011001001 !
b1001 $
b1001 &
#138
b10011001001111101110011100110010 !
b1010 $
b1010 &
#139
b0 !
b1011 $
b1011 &
#140
b1100 $
b1100 &
#141
b1100001100101101100100000000000 !
b1101 $
b1101 &
#142
b11111111111111011001010110000110 !
b1110 $
b1110 &
#143
b11101100101011000011001011011001 !
b1111 $
b1111 &
#144
b11111011100101000001001111110110 !
b0 $
b10001100110100110000001000011001 #
b1101110110000010001000111011101 "
b1100110100110000000011100111 '
b1001 %
b0 &
#145
b11100001111011100000111111000100 !
b1 $
b1 &
#146
b11101000001001010111100010010101 !
b10 $
b10 &
#147
b0 !
b11 $
b11 &
#148
b1101110110000010001000111011101 !
b100 $
b100 &
#149
b10001100110100110000001000011001 !
b101 $
b101 &
#150
b0 !
b110 $
b110 &
#151
b10010001001111101110111000100011 !
b111 $
b111 &
#152
b11101110110100110001001111011101 !
b1000 $
b1000 &
#153
b1100110000010000000000011001 !
b1001 $
b1001 &
#154
b11100010000100100001001111000100 !
b1010 $
b1010 &
#155
b1 !
b1011 $
b1011 &
#156
b0 !
b1100 $
b1100 &
#157
b10111010000000000000000000000000 !
b1101 $
b1101 &
#158
b110111 !
b1110 $
b1110 &
#159
b1101110110000010001000111011101 !
b1111 $
b1111 &
#160
b11100000100010010010010111000000 !
b0 $
b1100011100111101010111111000111 #
b1111100111010100111010111111001 "
b11100011100111101010110011001101 '
b1010 %
b0 &
#161
b11001010010111100011000110010 !
b1 $
b1 &
#162
b1111011100101001110101110001111 !
b10 $
b10 &
#163
b1 !
b11 $
b11 &
#164
b11001010010111100011000110010 !
b100 $
b100 &
#165
b1100011100111101010111111000111 !
b101 $
b101 &
#166
b100100010010010010001100001001 !
b110 $
b110 &
#167
b10000011000101011000101000000111 !
b111 $
b111 &
#168
b1111111111111101111111111111111 !
b1000 $
b1000 &
#169
b1100000100010100010010111000001 !
b1001 $
b1001 &
#170
b11111011101001101101000111110 !
b1010 $
b1010 &
#171
b1 !
b1011 $
b1011 &
#172
b0 !
b1100 $
b1100 &
#173
b1110101001110101111110010000000 !
b1101 $
b1101 &
#174
b111110011101010011101011 !
b1110 $
b1110 &
#175
b1111100111010100111010111111001 !
b1111 $
b1111 &
#176
b1101100001011010000010011011000 !
b0 $
b11101010100010010011101011010101 #
b10000001101000111100101000000011 "
b1101010100010010011100010100011 '
b1011 %
b0 &
#177
b10010111000110101000111100101110 !
b1 $
b1 &
#178
b11010010101001101100001001111111 !
b10 $
b10 &
#179
b101 !
b11 $
b11 &
#180
b11101100111101011010001111011010 !
b100 $
b100 &
#181
b11101010100010010011101011010101 !
b101 $
b101 &
#182
b0 !
b110 $
b110 &
#183
b1111110010111000011010111111101 !
b111 $
b111 &
#184
b11101011101010111111101011010111 !
b1000 $
b1000 &
#185
b10000000100000010000101000000001 !
b1001 $
b1001 &
#186
b1101011001010101111000011010110 !
b1010 $
b1010 &
#187
b0 !
b1011 $
b1011 &
#188
b1100 $
b1100 &
#189
b1000000011000000000000000000000 !
b1101 $
b1101 &
#190
b11111111111111111111110000001101 !
b1110 $
b1110 &
#191
b10000001101000111100101000000011 !
b1111 $
b1111 &
#192
b11100100000111110011000111000 !
b0 $
b11100000111100100001100111000 #
b11001011010001100000000 "
b10011100000111100100000111101001 '
b1100 %
b0 &
#193
b11100100010001110101111111001000 !
b1 $
b1 &
#194
b11001001111001001010100000000000 !
b10 $
b10 &
#195
b0 !
b11 $
b11 &
#196
b11001011010001100000000 !
b100 $
b100 &
#197
b11100000111100100001100111000 !
b101 $
b101 &
#198
b0 !
b110 $
b110 &
#199
b11111111100110100101110100000000 !
b111 $
b111 &
#200
b11100011111111110001100111000 !
b1000 $
b1000 &
#201
b1000000001100000000 !
b1001 $
b1001 &
#202
b11100011110111110000000111000 !
b1010 $
b1010 &
#203
b0 !
b1011 $
b1011 &
#204
b1100 $
b1100 &
#205
b1101 $
b1101 &
#206
b1110 $
b1110 &
#207
b11001011010001100000000 !
b1111 $
b1111 &
#208
b11100110110011111010001111001100 !
b0 $
b10010111010100110000010000101110 #
b1001111011111001001111110011110 "
b10111010100110000001000011111 '
b1101 %
b0 &
#209
b10111000001010011001101101110000 !
b1 $
b1 &
#210
b101101000111010010011001100100 !
b10 $
b10 &
#211
b0 !
b11 $
b11 &
#212
b1001111011111001001111110011110 !
b100 $
b100 &
#213
b10010111010100110000010000101110 !
b101 $
b101 &
#214
b0 !
b110 $
b110 &
#215
b10110000100000110110000001100010 !
b111 $
b111 &
#216
b11011111011111111001111110111110 !
b1000 $
b1000 &
#217
b111010100000000010000001110 !
b1001 $
b1001 &
#218
b11011000001011111001101110110000 !
b1010 $
b1010 &
#219
b1 !
b1011 $
b1011 &
#220
b0 !
b1100 $
b1100 &
#221
b100111111001111000000000000000 !
b1101 $
b1101 &
#222
b10011110111110010 !
b1110 $
b1110 &
#223
b1001111011111001001111110011110 !
b1111 $
b1111 &
#224
b100101000011111100000001000 !
b0 $
b10011101111011101011000000111011 #
b1100110101100110100011111001101 "
b11101111011101010111011000101 '
b1110 %
b0 &
#225
b11001000110001001001011110010010 !
b1 $
b1 &
#226
b1100110010001000111110000111111 !
b10 $
b10 &
#227
b11111111111111111111111111111111 !
b11 $
b11 &
#228
b100101000011111100000001000 !
b100 $
b100 &
#229
b10011101111011101011000000111011 !
b101 $
b101 &
#230
b0 !
b110 $
b110 &
#231
b10011001010011001011100000110011 !
b111 $
b111 &
#232
b11111111111111111111011111111111 !
b1000 $
b1000 &
#233
b100101000100000000000001001 !
b1001 $
b1001 &
#234
b11111011010111011111011111110110 !
b1010 $
b1010 &
#235
b1 !
b1011 $
b1011 &
#236
b0 !
b1100 $
b1100 &
#237
b1101000000000000000000000000000 !
b1101 $
b1101 &
#238
b1100 !
b1110 $
b1110 &
#239
b1100110101100110100011111001101 !
b1111 $
b1111 &
#240
b110101010010001101001001101010 !
b0 $
b11101111100000011101101011011111 #
b1000101110001101111011110001011 "
b1101111100000011101100101011011 '
b1111 %
b0 &
#241
b1010110010001010001110010101100 !
b1 $
b1 &
#242
b10111001001010010000000000010101 !
b10 $
b10 &
#243
b11111111111111111111111111111100 !
b11 $
b11 &
#244
b11110011100110001100000111 !
b100 $
b100 &
#245
b11101111100000011101101011011111 !
b101 $
b101 &
#246
b0 !
b110 $
b110 &
#247
b10111010001110010000100001110101 !
b111 $
b111 &
#248
b11101111110001111111111111011111 !
b1000 $
b1000 &
#249
b1000101100000001101001010001011 !
b1001 $
b1001 &
#250
b10101010010001110010110101010100 !
b1010 $
b1010 &
#251
b1 !
b1011 $
b1011 &
#252
b0 !
b1100 $
b1100 &
#253
b10000000000000000000000000000000 !
b1101 $
b1101 &
#254
b0 !
b1110 $
b1110 &
#255
b1000101110001101111011110001011 !
b1111 $
b1111 &
#256
b11101101001001000000000111010 !
b0 $
b11100001010001001101000011000010 #
b111100010111111010111101111000 "
b1100001010001001100111101100001 '
b10000 %
b0 &
#257
b1011011000110101101111010110110 !
b1 $
b1 &
#258
b10010010111101000111100011110000 !
b10 $
b10 &
#259
b11111111111111111111111111111111 !
b11 $
b11 &
#260
b11101101001001000000000111010 !
b100 $
b100 &
#261
b11100001010001001101000011000010 !
b101 $
b101 &
#262
b0 !
b110 $
b110 &
#263
b11000011101000000101000010001000 !
b111 $
b111 &
#264
b11111101010111111111111111111010 !
b1000 $
b1000 &
#265
b100000010001001000000001000000 !
b1001 $
b1001 &
#266
b11011101000110110111111110111010 !
b1010 $
b1010 &
#267
b1 !
b1011 $
b1011 &
#268
b0 !
b1100 $
b1100 &
#269
b11110001011111101011110111100000 !
b1101 $
b1101 &
#270
b1111000101111110101111011110 !
b1110 $
b1110 &
#271
b111100010111111010111101111000 !
b1111 $
b1111 &
#272
b1100010111101111111101011000101 !
b0 $
b10110000111101001111110001100001 #
b10110010000000101111111001100100 "
b110000111101001111101001010111 '
b10001 %
b0 &
#273
b1000011100000001000000011 !
b1 $
b1 &
#274
b10011100110111001101001111100100 !
b10 $
b10 &
#275
b0 !
b11 $
b11 &
#276
b10110010000000101111111001100100 !
b100 $
b100 &
#277
b10110000111101001111110001100001 !
b101 $
b101 &
#278
b0 !
b110 $
b110 &
#279
b1001101111111010000000110011100 !
b111 $
b111 &
#280
b10110010111101101111111001100101 !
b1000 $
b1000 &
#281
b10110000000000001111110001100000 !
b1001 $
b1001 &
#282
b10111101100000001000000101 !
b1010 $
b1010 &
#283
b1 !
b1011 $
b1011 &
#284
b0 !
b1100 $
b1100 &
#285
b1100100000001011111110011001000 !
b1101 $
b1101 &
#286
b11011001000000010111111100110010 !
b1110 $
b1110 &
#287
b10110010000000101111111001100100 !
b1111 $
b1111 &
#288
b11110011110000110010010111100111 !
b0 $
b11010100100010010100000010101001 #
b11111001110011110010100111110 "
b1010100100010010011111110111101 '
b10010 %
b0 &
#289
b1001010101100001010010010010101 !
b1 $
b1 &
#290
b11100101101011101010111101110 !
b10 $
b10 &
#291
b0 !
b11 $
b11 &
#292
b11111001110011110010100111110 !
b100 $
b100 &
#293
b11010100100010010100000010101001 !
b101 $
b101 &
#294
b0 !
b110 $
b110 &
#295
b11100000110001100001101011000010 !
b111 $
b111 &
#296
b11011111101110011110010110111111 !
b1000 $
b1000 &
#297
b10100000010010100000000101000 !
b1001 $
b1001 &
#298
b11001011101100001010010110010111 !
b1010 $
b1010 &
#299
b1 !
b1011 $
b1011 &
#300
b0 !
b1100 $
b1100 &
#301
b1110011110010100111110000000000 !
b1101 $
b1101 &
#302
b11111001110011110010 !
b1110 $
b1110 &
#303
b11111001110011110010100111110 !
b1111 $
b1111 &
#304
b1001100001101110000100010010111 !
b0 $
b11100010010101010110001011000100 #
b1101001111000011010010111010011 "
b1100010010101010110000100010011 '
b10011 %
b0 &
#305
b10000111100011000100001100001111 !
b1 $
b1 &
#306
b11000111010011001011101110001100 !
b10 $
b10 &
#307
b11111111111111111111111111111101 !
b11 $
b11 &
#308
b10000111000011100111000011111 !
b100 $
b100 &
#309
b11100010010101010110001011000100 !
b101 $
b101 &
#310
b0 !
b110 $
b110 &
#311
b10010110000111100101101000101101 !
b111 $
b111 &
#312
b11101011111101011110011111010111 !
b1000 $
b1000 &
#313
b1100000010000010010000011000000 !
b1001 $
b1001 &
#314
b10001011101101001100011100010111 !
b1010 $
b1010 &
#315
b1 !
b1011 $
b1011 &
#316
b0 !
b1100 $
b1100 &
#317
b10011110000110100101110100110000 !
b1101 $
b1101 &
#318
b110100111100001101001011101 !
b1110 $
b1110 &
#319
b1101001111000011010010111010011 !
b1111 $
b1111 &
#320
b10010101000001001000000011 !
b0 $
b1100111101000101110100011001 #
b11110101010111111011010011101010 "
b10001100111101000101101111011001 '
b10100 %
b0 &
#321
b11101000011010110101011111010001 !
b1 $
b1 &
#322
b100010000110011010110011011010 !
b10 $
b10 &
#323
b0 !
b11 $
b11 &
#324
b11110101010111111011010011101010 !
b100 $
b100 &
#325
b1100111101000101110100011001 !
b101 $
b101 &
#326
b0 !
b110 $
b110 &
#327
b1010101000000100101100010110 !
b111 $
b111 &
#328
b11111101111111111111110111111011 !
b1000 $
b1000 &
#329
b100010101000001010000001000 !
b1001 $
b1001 &
#330
b11111001101010111110100111110011 !
b1010 $
b1010 &
#331
b0 !
b1011 $
b1011 &
#332
b1100 $
b1100 &
#333
b11010100000000000000000000000000 !
b1101 $
b1101 &
#334
b11111111111111111111111111111010 !
b1110 $
b1110 &
#335
b11110101010111111011010011101010 !
b1111 $
b1111 &
#336
b101000010000100101111001010000 !
b0 $
b100000100011100101100001000 #
b100100001100001001001101001000 "
b10000100000100011100100110001111 '
b10101 %
b0 &
#337
b100000000111101100100001000000 !
b1 $
b1 &
#338
b10001110000101101011001001000000 !
b10 $
b10 &
#339
b1000 !
b11 $
b11 &
#340
b11101000100011101100001000 !
b100 $
b100 &
#341
b100000100011100101100001000 !
b101 $
b101 &
#342
b0 !
b110 $
b110 &
#343
b11011011110011110110110010111000 !
b111 $
b111 &
#344
b100100001100011101101101001000 !
b1000 $
b1000 &
#345
b100000100001000001100001000 !
b1001 $
b1001 &
#346
b100000001000010101100001000000 !
b1010 $
b1010 &
#347
b1 !
b1011 $
b1011 &
#348
b0 !
b1100 $
b1100 &
#349
b110000100100110100100000000000 !
b1101 $
b1101 &
#350
b1001000011000010010011 !
b1110 $
b1110 &
#351
b100100001100001001001101001000 !
b1111 $
b1111 &
#352
b10111001111100111110110101110011 !
b0 $
b11000110111010100100000010001101 #
b11110011000010011010110011100110 "
b1000110111010100011111110110101 '
b10110 %
b0 &
#353
b101100000111110110110001011001 !
b1 $
b1 &
#354
b110101110010011011101010101110 !
b10 $
b10 &
#355
b0 !
b11 $
b11 &
#356
b11110011000010011010110011100110 !
b100 $
b100 &
#357
b11000110111010100100000010001101 !
b101 $
b101 &
#358
b0 !
b110 $
b110 &
#359
b1100111101100101001100011010 !
b111 $
b111 &
#360
b11110111111010111110110011101111 !
b1000 $
b1000 &
#361
b11000010000010000000000010000100 !
b1001 $
b1001 &
#362
b110101111000111110110001101011 !
b1010 $
b1010 &
#363
b1 !
b1011 $
b1011 &
#364
b0 !
b1100 $
b1100 &
#365
b110101100111001100000000000000 !
b1101 $
b1101 &
#366
b11111111111111111001100001001101 !
b1110 $
b1110 &
#367
b11110011000010011010110011100110 !
b1111 $
b1111 &
#368
b11110101101000001110011111101011 !
b0 $
b10000111000110101011000000001110 #
b1101110100001100011011111011101 "
b111000110101010111111001011 '
b10111 %
b0 &
#369
b11100111011010111000011111001111 !
b1 $
b1 &
#370
b10001001001100001111111000010110 !
b10 $
b10 &
#371
b0 !
b11 $
b11 &
#372
b1101110100001100011011111011101 !
b100 $
b100 &
#373
b10000111000110101011000000001110 !
b101 $
b101 &
#374
b0 !
b110 $
b110 &
#375
b10010001011110011100100000100011 !
b111 $
b111 &
#376
b11101111100111101011011111011111 !
b1000 $
b1000 &
#377
b110000000100011000000001100 !
b1001 $
b1001 &
#378
b11101001100111001000011111010011 !
b1010 $
b1010 &
#379
b1 !
b1011 $
b1011 &
#380
b0 !
b1100 $
b1100 &
#381
b10001101111101110100000000000000 !
b1101 $
b1101 &
#382
b11011101000011000 !
b1110 $
b1110 &
#383
b1101110100001100011011111011101 !
b1111 $
b1111 &
#384
b11001101001011011101111110011010 !
b0 $
b10010010000101101100100000100100 #
b111011000101110001011101110110 "
b10010000101101100011101010001 '
b11000 %
b0 &
#385
b10101001000000000100111101010010 !
b1 $
b1 &
#386
b10101001101101110111110010011000 !
b10 $
b10 &
#387
b0 !
b11 $
b11 &
#388
b111011000101110001011101110110 !
b100 $
b100 &
#389
b10010010000101101100100000100100 !
b101 $
b101 &
#390
b0 !
b110 $
b110 &
#391
b11000100111010001110100010001010 !
b111 $
b111 &
#392
b10111011000101111101111101110110 !
b1000 $
b1000 &
#393
b10010000101100000000000100100 !
b1001 $
b1001 &
#394
b10101001000000011101111101010010 !
b1010 $
b1010 &
#395
b1 !
b1011 $
b1011 &
#396
b0 !
b1100 $
b1100 &
#397
b10110001011100010111011101100000 !
b1101 $
b1101 &
#398
b11101100010111000101110111 !
b1110 $
b1110 &
#399
b111011000101110001011101110110 !
b1111 $
b1111 &
#400
b110001000011000000110001100001 !
b0 $
b1000101010111100101000110001010 #
b11101011101011011011101011010111 "
b11000101010111100100111111000111 '
b11001 %
b0 &
#401
b10100110010011110110100101001101 !
b1 $
b1 &
#402
b10010001101101101011111011100110 !
b10 $
b10 &
#403
b0 !
b11 $
b11 &
#404
b11101011101011011011101011010111 !
b100 $
b100 &
#405
b1000101010111100101000110001010 !
b101 $
b101 &
#406
b1010001100100011011100011010001 !
b110 $
b110 &
#407
b10100010100100100010100101001 !
b111 $
b111 &
#408
b11101111111111111111101111011111 !
b1000 $
b1000 &
#409
b1000001000011000001000010000010 !
b1001 $
b1001 &
#410
b10101110111100111110101101011101 !
b1010 $
b1010 &
#411
b0 !
b1011 $
b1011 &
#412
b1100 $
b1100 &
#413
b10110110111010110101110000000000 !
b1101 $
b1101 &
#414
b11111111111110101110101101101110 !
b1110 $
b1110 &
#415
b11101011101011011011101011010111 !
b1111 $
b1111 &
#416
b1101011101000111000111011010110 !
b0 $
b11000101010010011001000010001010 #
b10100110010110011111111001001100 "
b1000101010010011000111010101101 '
b11010 %
b0 &
#417
b11100001000100000110110111000010 !
b1 $
b1 &
#418
b1001011001110011101010011111000 !
b10 $
b10 &
#419
b1 !
b11 $
b11 &
#420
b11100001000100000110110111000010 !
b100 $
b100 &
#421
b11000101010010011001000010001010 !
b101 $
b101 &
#422
b0 !
b110 $
b110 &
#423
b1011001101001100000000110110100 !
b111 $
b111 &
#424
b11100111010110011111111011001110 !
b1000 $
b1000 &
#425
b10000100010010011001000000001000 !
b1001 $
b1001 &
#426
b1100011000100000110111011000110 !
b1010 $
b1010 &
#427
b0 !
b1011 $
b1011 &
#428
b1100 $
b1100 &
#429
b1100111111110010011000000000000 !
b1101 $
b1101 &
#430
b11111111111010011001011001111111 !
b1110 $
b1110 &
#431
b10100110010110011111111001001100 !
b1111 $
b1111 &
#432
b10111110110101111011001101111101 !
b0 $
b1111000000001001010011111110000 #
b1000110110100110000101110001101 "
b11111000000001001010010110000011 '
b11011 %
b0 &
#433
b11001110110011100110001110011101 !
b1 $
b1 &
#434
b1011000100101111100111100110000 !
b10 $
b10 &
#435
b0 !
b11 $
b11 &
#436
b1000110110100110000101110001101 !
b100 $
b100 &
#437
b1111000000001001010011111110000 !
b101 $
b101 &
#438
b10011101110100101111001111000001 !
b110 $
b110 &
#439
b10111001001011001111010001110011 !
b111 $
b111 &
#440
b1111110110101111010111111111101 !
b1000 $
b1000 &
#441
b1000000000000000000001110000000 !
b1001 $
b1001 &
#442
b111110110101111010110001111101 !
b1010 $
b1010 &
#443
b0 !
b1011 $
b1011 &
#444
b1100 $
b1100 &
#445
b1011100011010000000000000000 !
b1101 $
b1101 &
#446
b100011011010011 !
b1110 $
b1110 &
#447
b1000110110100110000101110001101 !
b1111 $
b1111 &
#448
b10010011101101010010010100100111 !
b0 $
b10010110000100011111001000101100 #
b11111101101000110011001011111011 "
b10110000100011111000111001001 '
b11100 %
b0 &
#449
b1100111100100010100000011001111 !
b1 $
b1 &
#450
b1010010111010010000100100100100 !
b10 $
b10 &
#451
b0 !
b11 $
b11 &
#452
b11111101101000110011001011111011 !
b100 $
b100 &
#453
b10010110000100011111001000101100 !
b101 $
b101 &
#454
b0 !
b110 $
b110 &
#455
b10010111001100110100000101 !
b111 $
b111 &
#456
b11111111101100111111001011111111 !
b1000 $
b1000 &
#457
b10010100000000010011001000101000 !
b1001 $
b1001 &
#458
b1101011101100101100000011010111 !
b1010 $
b1010 &
#459
b1 !
b1011 $
b1011 &
#460
b0 !
b1100 $
b1100 &
#461
b110011001011111011000000000000 !
b1101 $
b1101 &
#462
b11111111111111111101101000110011 !
b1110 $
b1110 &
#463
b11111101101000110011001011111011 !
b1111 $
b1111 &
#464
b1101110110110100100010011011100 !
b0 $
b1100111011010110110111111001110 #
b111011011101101010100001110 "
b11100111011010110110110011111111 '
b11101 %
b0 &
#465
b10100000000000110110010101000000 !
b1 $
b1 &
#466
b10111000011010101000001101000100 !
b10 $
b10 &
#467
b0 !
b11 $
b11 &
#468
b111011011101101010100001110 !
b100 $
b100 &
#469
b1100111011010110110111111001110 !
b101 $
b101 &
#470
b0 !
b110 $
b110 &
#471
b11111000100100010010101011110010 !
b111 $
b111 &
