test_designs/adffe/adffe.v


module adffe(
	input clk_i,
	input rst_i,
	input en_i,
	input [31:0] data_i,
	output reg [31:0] q_o
);
	always @(posedge clk_i or posedge rst_i) begin
		if (rst_i) begin
			q_o <= 0;
		end else if (en_i) begin
			q_o <= data_i;
		end
	end
endmodule

test_designs/adffe/adffe_tb.v
`include "adffe.v"

module tb;
	reg           clk_i;
	reg           rst_i;
	reg           en_i;
	reg [31:0]    data_i;
	wire [31:0]   q_o;

	adffe dut (
		.clk_i(clk_i),
		.rst_i(rst_i),
		.en_i(en_i),
		.data_i(data_i),
		.q_o(q_o)
	);
	integer seed;
	integer i;
	initial begin
		seed = 123;
		$dumpfile(".adffe_tb.vcd");
		$dumpvars(1, tb);
		clk_i = 0;
		rst_i = 1;
		en_i = 0;
		data_i = 0;

		#1;
		rst_i = 0;

		for (i = 0; i < 1000; i+= 1) begin
			rst_i = $random(seed);
			en_i = $random(seed);
			data_i = $random(seed);
			clk_i = 0;
			#1;
			clk_i = 1;
			#1;
		end
	end

endmodule

test_designs/adffe/.adffe_tb.vcd
$date
	Wed Oct 22 23:46:03 2025
$end
$version
	Icarus Verilog
$end
$timescale
	1s
$end
$scope module tb $end
$var wire 32 ! q_o [31:0] $end
$var reg 1 " clk_i $end
$var reg 32 # data_i [31:0] $end
$var reg 1 $ en_i $end
$var reg 1 % rst_i $end
$var integer 32 & i [31:0] $end
$var integer 32 ' seed [31:0] $end
$upscope $end
$enddefinitions $end
$comment Show the parameter values. $end
$dumpall
$end
#0
$dumpvars
b1111011 '
bx &
1%
0$
b0 #
0"
b0 !
$end
#1
b11011001001101001110110010110010 #
1$
b1011001001101001110101101001110 '
b0 &
1%
#2
1"
#3
0"
b11001100100110101101011010011001 #
b1001100100110101101010111011101 '
b1 &
#4
1"
#5
0"
b11110001110110011111110011100011 #
0$
b1110001110110011111101111011000 '
b10 &
#6
1"
#7
0"
b10101101111110000001100001011011 #
0%
b101101111110000001011010101111 '
b11 &
#8
1"
#9
0"
b1100101111100011100001111001011 #
1%
b11100101111100011100000010010010 '
b100 &
#10
1"
#11
0"
b1110101100100101101010111101011 #
1$
b11110101100100101101001101110001 '
b101 &
#12
1"
#13
0"
b1111100111010100111010111111001 #
b11111100111010100111001111111100 '
b110 &
#14
1"
#15
0"
b11101010100010010011101011010101 #
b1101010100010010011100010100011 '
b111 &
#16
1"
#17
0"
b1001111011111001001111110011110 #
0$
0%
b11001111011111001001110010010110 '
b1000 &
#18
1"
#19
0"
b10011101111011101011000000111011 #
1$
b11101111011101010111011000101 '
b1001 &
#20
b10011101111011101011000000111011 !
1"
#21
b0 !
0"
b111100010111111010111101111000 #
1%
b10111100010111111010110011100000 '
b1010 &
#22
1"
#23
0"
b10110000111101001111110001100001 #
0$
0%
b110000111101001111101001010111 '
b1011 &
#24
1"
#25
0"
b1101001111000011010010111010011 #
1$
b11101001111000011010001101011010 '
b1100 &
#26
b1101001111000011010010111010011 !
1"
#27
0"
b1100111101000101110100011001 #
0$
b10001100111101000101101111011001 '
b1101 &
#28
1"
#29
0"
b11110011000010011010110011100110 #
b1110011000010011010101010000100 '
b1110 &
#30
1"
#31
b0 !
0"
b10000111000110101011000000001110 #
1$
1%
b111000110101010111111001011 '
b1111 &
#32
1"
#33
0"
b11101011101011011011101011010111 #
0$
0%
b1101011101011011011100011011110 '
b10000 &
#34
1"
#35
0"
b11000101010010011001000010001010 #
b1000101010010011000111010101101 '
b10001 &
#36
1"
#37
0"
b11111101101000110011001011111011 #
1%
b1111101101000110011000011101000 '
b10010 &
#38
1"
#39
0"
b1100111011010110110111111001110 #
0%
b11100111011010110110110011111111 '
b10011 &
#40
1"
#41
0"
b110001111100101000001101100011 #
1%
b10110001111100101000000100100010 '
b10100 &
#42
1"
#43
0"
b11101000010001111011110011010000 #
b1101000010001111011101101000001 '
b10101 &
#44
1"
#45
0"
b110011101101011100011101100111 #
0%
b10110011101101011100010000001100 '
b10110 &
#46
1"
#47
0"
b1001010100111100000011110010101 #
1$
1%
b11001010100111100000010111110011 '
b10111 &
#48
1"
#49
0"
b101111000010100110001101011110 #
b10101111000010100110000000100110 '
b11000 &
#50
1"
#51
0"
b11101011000100000001011011010110 #
0$
0%
b1101011000100000001010110010101 '
b11001 &
#52
1"
#53
0"
b1101001111011010100100011010 #
1$
1%
b10001101001111011010011111110000 '
b11010 &
#54
1"
#55
0"
b100101001000110001000101001010 #
b10100101001000110000111010100111 '
b11011 &
#56
1"
#57
0"
b1101000000111000111101111010000 #
0%
b11101000000111000111100111101010 '
b11100 &
#58
b1101000000111000111101111010000 !
1"
#59
b0 !
0"
b11010001010111111001001010100010 #
0$
1%
b1010001010111111001000110101001 '
b11101 &
#60
1"
#61
0"
b11010001000011011110001010100010 #
1$
b1010001000011011110000010010100 '
b11110 &
#62
1"
#63
0"
b1101100010110001101110111011000 #
0%
b11101100010110001101101100011011 '
b11111 &
#64
b1101100010110001101110111011000 !
1"
#65
0"
b100101011000001011010101001010 #
b10100101011000001011001001101110 '
b100000 &
#66
b100101011000001011010101001010 !
1"
#67
b0 !
0"
b11100010001000101110010011000100 #
1%
b1100010001000101110001101111101 '
b100001 &
#68
1"
#69
0"
b1001111111101000011001110011111 #
0$
b11001111111101000011000111111000 '
b100010 &
#70
1"
#71
0"
b11110111011111111000000011101110 #
0%
b1110111011111110111111101001111 '
b100011 &
#72
1"
#73
0"
b111001001000111010111101110010 #
1%
b10111001001000111010110110110010 '
b100100 &
#74
1"
#75
0"
b1001110010101000000100010011 #
1$
0%
b10001001110010100111111100010001 '
b100101 &
#76
b1001110010101000000100010011 !
1"
#77
b0 !
0"
b1110000100111010010001111100001 #
1%
b11110000100111010010000000011100 '
b100110 &
#78
1"
#79
0"
b11010000011011001101000010100000 #
b1010000011011001100111101000011 '
b100111 &
#80
1"
#81
0"
b10000001100010101101000000000011 #
b1100010101100111110110110 '
b101000 &
#82
1"
#83
0"
b11011110010111101001101010111100 #
0%
b1011110010111101001100001100101 '
b101001 &
#84
b11011110010111101001101010111100 !
1"
#85
b0 !
0"
b10010000001101111111000000100000 #
0$
1%
b10000001101111110111100000000 '
b101010 &
#86
1"
#87
0"
b1001000000000000110000110010000 #
b11001000000000000101111011110111 '
b101011 &
#88
1"
#89
0"
b1001000110000011111100010010 #
1$
0%
b10001001000110000011110001111010 '
b101100 &
#90
b1001000110000011111100010010 !
1"
#91
b0 !
0"
b11111001010100110010010011110010 #
1%
b1111001010100110010001101111001 '
b101101 &
#92
1"
#93
0"
b1111011110110101010010111110111 #
0$
b11111011110110101010001010100100 '
b101110 &
#94
1"
#95
0"
b1100010010101111000010111000100 #
b11100010010101111000001001101011 '
b101111 &
#96
1"
#97
0"
b1101001111011101101100111010011 #
1$
0%
b11101001111011101101011111111110 '
b110000 &
#98
b1101001111011101101100111010011 !
1"
#99
0"
b11011000110111101011100110110 #
0$
b10011011000110111101010001001101 '
b110001 &
#100
1"
#101
0"
b10000110101001100000000000001101 #
1$
b110101001011111111100001000 '
b110010 &
#102
b10000110101001100000000000001101 !
1"
#103
b0 !
0"
b1101110110000010100111111011101 #
1%
b11101110110000010100110110011111 '
b110011 &
#104
1"
#105
0"
b11010111110101100100100010101111 #
0$
0%
b1010111110101100100011001000010 '
b110100 &
#106
1"
#107
0"
b1001100100000000010000110011001 #
b11001100100000000001111011100001 '
b110101 &
#108
1"
#109
0"
b101010011000101100000001 #
b10000000101010011000100000101100 '
b110110 &
#110
1"
#111
0"
b1011111011100101001011110111110 #
1%
b11011111011100101001010010010011 '
b110111 &
#112
1"
#113
0"
b11110100111111101110110011101001 #
b1110100111111101110101101000110 '
b111000 &
#114
1"
#115
0"
b11110001101011110011100011100011 #
0%
b1110001101011110011011100110101 '
b111001 &
#116
1"
#117
0"
b10010100001111000010100100101 #
1$
b10010010100001111000001000010000 '
b111010 &
#118
b10010100001111000010100100101 !
1"
#119
0"
b110100111110011110110101101001 #
0$
b10110100111110011110101101000111 '
b111011 &
#120
1"
#121
0"
b1010101100001011110110110101011 #
1$
b11010101100001011110101100001010 '
b111100 &
#122
b1010101100001011110110110101011 !
1"
#123
0"
b10000011000101000001001000000110 #
0$
b11000101000001000101001001 '
b111101 &
#124
1"
#125
0"
b11000001110110001111001010000011 #
b1000001110110001111000010110100 '
b111110 &
#126
1"
#127
b0 !
0"
b10010001011100111010011000100010 #
1$
1%
b10001011100111010010110111011 '
b111111 &
#128
1"
#129
0"
b1010101101110010010101110101011 #
0$
b11010101101110010010100110001110 '
b1000000 &
#130
1"
#131
0"
b1011111111010010110001110111111 #
1$
b11011111111010010110000100011101 '
b1000001 &
#132
1"
#133
0"
b10100010010100011001101001000100 #
0$
b100010010100011001100000011000 '
b1000010 &
#134
1"
#135
0"
b1000111011111011101100110001110 #
0%
b11000111011111011101011111101111 '
b1000011 &
#136
1"
#137
0"
b10100111000110110100110001001110 #
1$
1%
b100111000110110100101011010010 '
b1000100 &
#138
1"
#139
0"
b11101110100011011001110011011101 #
0$
0%
b1101110100011011001101010110001 '
b1000101 &
#140
1"
#141
0"
b1110111101000111111111111101111 #
1$
1%
b11110111101000111111110000111100 '
b1000110 &
#142
1"
#143
0"
b1111000111011000101011111110001 #
0$
0%
b11111000111011000101010111100011 '
b1000111 &
#144
1"
#145
0"
b10111000001001111011010001110000 #
1%
b111000001001111011001011010110 '
b1001000 &
#146
1"
#147
0"
b11111110100101101111010011111101 #
b1111110100101101111001000000101 '
b1001001 &
#148
1"
#149
0"
b11001100001001010110001010011000 #
0%
b1001100001001010110000100100000 '
b1001010 &
#150
1"
#151
0"
b10011001001111001011010000110010 #
1$
1%
b11001001111001011001110010111 '
b1001011 &
#152
1"
#153
0"
b11011010110101101000011010110101 #
0$
0%
b1011010110101101000010110011010 '
b1001100 &
#154
1"
#155
0"
b100000101001110101110101000001 #
1$
b10100000101001110101101100011001 '
b1001101 &
#156
b100000101001110101110101000001 !
1"
#157
b0 !
0"
b1000000001100011100110110000000 #
0$
1%
b11000000001100011100101011000100 '
b1001110 &
#158
1"
#159
0"
b1100111110010100100011111001111 #
1$
b11100111110010100100010100001011 '
b1001111 &
#160
1"
#161
0"
b11001101111000001010100010011011 #
0$
b1001101111000001010011100011110 '
b1010000 &
#162
1"
#163
0"
b1101000000000001000101111010000 #
b11101000000000001000100111101101 '
b1010001 &
#164
1"
#165
0"
b10110010011111111111100101100 #
0%
b10010110010011111111110100101000 '
b1010010 &
#166
1"
#167
0"
b10110101110000100010000001101011 #
b110101110000100001111000111111 '
b1010011 &
#168
1"
#169
0"
b1100110000111011110100011001 #
1$
b10001100110000111011101101100010 '
b1010100 &
#170
b1100110000111011110100011001 !
1"
#171
b0 !
0"
b11001001110101111111010010010011 #
0$
1%
b1001001110101111111001010000001 '
b1010101 &
#172
1"
#173
0"
b1000000000101010111111110000000 #
1$
b11000000000101010111110001001100 '
b1010110 &
#174
1"
#175
0"
b10001011110101110001010000010111 #
b1011110101110001001100110011 '
b1010111 &
#176
1"
#177
0"
b1010100001100010100100010101 #
0%
b10001010100001100010011001100110 '
b1011000 &
#178
b1010100001100010100100010101 !
1"
#179
b0 !
0"
b1110011010101100101100011100 #
0$
1%
b10001110011010101100100011010101 '
b1011001 &
#180
1"
#181
0"
b11101111110010101000111011011111 #
1$
b1101111110010101000110000110000 '
b1011010 &
#182
1"
#183
0"
b11101101011011100100000111 #
b10000011101101011011011111100111 '
b1011011 &
#184
1"
#185
0"
b111011001110110000111101110110 #
0$
b10111011001110110000110000101010 '
b1011100 &
#186
1"
#187
0"
b111110100100000001100001111 #
1$
0%
b10000111110100100000000011101001 '
b1011101 &
#188
b111110100100000001100001111 !
1"
#189
0"
b1110010110011100011001111100101 #
0$
b11110010110011100011000011010100 '
b1011110 &
#190
1"
#191
0"
b11101001001110000110001011010010 #
b1101001001110000110000001011011 '
b1011111 &
#192
1"
#193
0"
b10010000010001100101001000100000 #
1$
b10000010001100101000010101110 '
b1100000 &
#194
b10010000010001100101001000100000 !
1"
#195
0"
b10000010100101100101000000000101 #
0$
b10100101100100111010111101 '
b1100001 &
#196
1"
#197
0"
b11011000101110100011000010110001 #
b1011000101110100010111000111000 '
b1100010 &
#198
1"
#199
b0 !
0"
b11110111010110110010001011101110 #
1%
b1110111010110110010000010001111 '
b1100011 &
#200
1"
#201
0"
b11001011011000001001100010010110 #
1$
0%
b1001011011000001001011111110010 '
b1100100 &
#202
b11001011011000001001100010010110 !
1"
#203
0"
b100100000001000010100101001000 #
b10100100000001000010011001010001 '
b1100101 &
#204
b100100000001000010100101001000 !
1"
#205
b0 !
0"
b10101011010001110000101001010110 #
0$
1%
b101011010001110000100001011100 '
b1100110 &
#206
1"
#207
0"
b1000100111011111100111110001001 #
1$
b11000100111011111100110010000011 '
b1100111 &
#208
1"
#209
0"
b11001100010110110100011010011000 #
b1001100010110110100010111110110 '
b1101000 &
#210
1"
#211
0"
b101010001111111011110101010100 #
0$
b10101010001111111011101110100101 '
b1101001 &
#212
1"
#213
0"
b10111010111100000000010001110101 #
0%
b111010111100000000001101000000 '
b1101010 &
#214
1"
#215
0"
b110101000100011111101101101010 #
1$
1%
b10110101000100011111100000110111 '
b1101011 &
#216
1"
#217
0"
b10111101101001001000000001111011 #
0$
0%
b111101101001000111111010111010 '
b1101100 &
#218
1"
#219
0"
b11000010000110010000010010000100 #
1$
1%
b1000010000110010000001010111001 '
b1101101 &
#220
1"
#221
0"
b11000100010101110010010010001000 #
b1000100010101110010001011100100 '
b1101110 &
#222
1"
#223
0"
b11111111010110101111100011111110 #
0$
0%
b1111111010110101111011110101011 '
b1101111 &
#224
1"
#225
0"
b11000011100010110010100010000111 #
1$
b1000011100010110010011000111110 '
b1110000 &
#226
b11000011100010110010100010000111 !
1"
#227
b0 !
0"
b1100110100111111011000111001101 #
0$
1%
b11100110100111111010111110001101 '
b1110001 &
#228
1"
#229
0"
b1110010011010010010110111100100 #
1$
0%
b11110010011010010010101101001000 '
b1110010 &
#230
b1110010011010010010110111100100 !
1"
#231
b0 !
0"
b10100011110101011110000001000111 #
1%
b100011110101011101111011011111 '
b1110011 &
#232
1"
#233
0"
b10010010010000101110001000100100 #
0%
b10010010000101110000010000010 '
b1110100 &
#234
b10010010010000101110001000100100 !
1"
#235
0"
b1111110011101110011100111111100 #
b11111110011101110011011000100001 '
b1110101 &
#236
b1111110011101110011100111111100 !
1"
#237
0"
b1010000011010001100000010 #
0$
b10000001010000011010000001101100 '
b1110110 &
#238
1"
#239
0"
b11011110101100111000001010111101 #
1$
b1011110101100111000000111010011 '
b1110111 &
#240
b11011110101100111000001010111101 !
1"
#241
0"
b1110101010000001001100011101 #
0$
b10001110101010000001000110000110 '
b1111000 &
#242
1"
#243
b0 !
0"
b101010111010101100110101010101 #
1%
b10101010111010101100101001110101 '
b1111001 &
#244
1"
#245
0"
b10000101110011101100100000001011 #
b101110011101100011001010000 '
b1111010 &
#246
1"
#247
0"
b1101111101111100111011111011111 #
b11101111101111100111010010000111 '
b1111011 &
#248
1"
#249
0"
b11011101110000111101111010111011 #
1$
b1011101110000111101110101001010 '
b1111100 &
#250
1"
#251
0"
b11111100110000010110001011111001 #
0%
b1111100110000010110000010001001 '
b1111101 &
#252
b11111100110000010110001011111001 !
1"
#253
0"
b10011110001101011010001000111100 #
b11110001101011010000011110100 '
b1111110 &
#254
b10011110001101011010001000111100 !
1"
#255
0"
b11001001100011110000110010010011 #
b1001001100011110000101011111011 '
b1111111 &
#256
b11001001100011110000110010010011 !
1"
#257
0"
b10000111000100000010100000001110 #
0$
b111000100000010011111001110 '
b10000000 &
#258
1"
#259
b0 !
0"
b10110100011010111100000101 #
1$
1%
b10000010110100011010110001011101 '
b10000001 &
#260
1"
#261
0"
b1110111101011111011100011101 #
0$
0%
b10001110111101011111010001011000 '
b10000010 &
#262
1"
#263
0"
b11111100011111110101101011111000 #
1%
b1111100011111110101100100101111 '
b10000011 &
#264
1"
#265
0"
b10001101011110111001011000011010 #
1$
b1101011110111001010100010010 '
b10000100 &
#266
1"
#267
0"
b1100110010101100010001111001100 #
b11100110010101100010000111110001 '
b10000101 &
#268
1"
#269
0"
b10010000110011100100011000100001 #
0$
b10000110011100100010001111100 '
b10000110 &
#270
1"
#271
0"
b1110001010111110011010111100010 #
0%
b11110001010111110011001100100011 '
b10000111 &
#272
1"
#273
0"
b10100011001011011000101001000110 #
1$
1%
b100011001011011000100100010110 '
b10001000 &
#274
1"
#275
0"
b10001001000000001111011000010010 #
0$
b1001000000001111010101000101 '
b10001001 &
#276
1"
#277
0"
b11010011010111111101011010100110 #
1$
0%
b1010011010111111101010101100000 '
b10001010 &
#278
b11010011010111111101011010100110 !
1"
#279
b0 !
0"
b11000111111010000010111010001111 #
1%
b1000111111010000010110011010111 '
b10001011 &
#280
1"
#281
0"
b11011100000010100010100010111000 #
0%
b1011100000010100010011111011010 '
b10001100 &
#282
b11011100000010100010100010111000 !
1"
#283
0"
b1011000110100000001110110110001 #
b11011000110100000001101001011001 '
b10001101 &
#284
b1011000110100000001110110110001 !
1"
#285
0"
b1111000100100101010110111110001 #
0$
b11111000100100101010101100000100 '
b10001110 &
#286
1"
#287
0"
b11101100111100011001110011011001 #
1$
b1101100111100011001101001001011 '
b10001111 &
#288
b11101100111100011001110011011001 !
1"
#289
b0 !
0"
b10000010111101100101011000000101 #
1%
b10111101100101010101011110 '
b10010000 &
#290
1"
#291
0"
b1001101101000010100011110011011 #
0$
b11001101101000010100010100101101 '
b10010001 &
#292
1"
#293
0"
b10001100101110011000101000011001 #
b1100101110011000100101101000 '
b10010010 &
#294
1"
#295
0"
b111100011001001001000101111000 #
1$
b10111100011001001000111101111111 '
b10010011 &
#296
1"
#297
0"
b11110101110110111011011011101011 #
0%
b1110101110110111011010110100010 '
b10010100 &
#298
b11110101110110111011011011101011 !
1"
#299
b0 !
0"
b1000100100001011110101110001001 #
1%
b11000100100001011110100111000001 '
b10010101 &
#300
1"
#301
0"
b10111111011101011111011001111110 #
b111111011101011111010010001100 '
b10010110 &
#302
1"
#303
0"
b1000010111011111110001110000101 #
0%
b11000010111011111110000001110011 '
b10010111 &
#304
b1000010111011111110001110000101 !
1"
#305
b0 !
0"
b10101100011011001010111001011000 #
0$
1%
b101100011011001010110010100110 '
b10011000 &
#306
1"
#307
0"
b101100110101110011111101011001 #
0%
b10101100110101110011110000010101 '
b10011001 &
#308
1"
#309
0"
b1100001010111000011001111000010 #
b11100001010111000011000001110000 '
b10011010 &
#310
1"
#311
0"
b1110011011111000010001111100110 #
1$
1%
b11110011011111000010000100100111 '
b10011011 &
#312
1"
#313
0"
b1001101101010000110000110011011 #
0%
b11001101101010000101111001101010 '
b10011100 &
#314
b1001101101010000110000110011011 !
1"
#315
0"
b111011000010100011001101110110 #
b10111011000010100011000000101001 '
b10011101 &
#316
b111011000010100011001101110110 !
1"
#317
b0 !
0"
b11101010010101110100001011010100 #
1%
b1101010010101110100000100010100 '
b10011110 &
#318
1"
#319
0"
b11100100010111111010011011001000 #
0%
b1100100010111111010010110011011 '
b10011111 &
#320
b11100100010111111010011011001000 !
1"
#321
b0 !
0"
b1111000000111101011000111110000 #
1%
b11111000000111101010111011101110 '
b10100000 &
#322
1"
#323
0"
b10101010000110111101100101010 #
0$
0%
b10010101010000110111100111111101 '
b10100001 &
#324
1"
#325
0"
b10001100110011001110110000011001 #
b1100110011001110101001111000 '
b10100010 &
#326
1"
#327
0"
b11101000010100101000001011010000 #
b1101000010100101000000111001111 '
b10100011 &
#328
1"
#329
0"
b10100000111101000100010001000001 #
b100000111101000100001000110010 '
b10100100 &
#330
1"
#331
0"
b101101101010111000111101011011 #
1$
b10101101101010111000110110010001 '
b10100101 &
#332
b101101101010111000111101011011 !
1"
#333
0"
b11001100000011011001100110011 #
b10011001100000011011000010011100 '
b10100110 &
#334
b11001100000011011001100110011 !
1"
#335
0"
b10111001000101000101100101110 #
b10010111001000101000100111000011 '
b10100111 &
#336
b10111001000101000101100101110 !
1"
#337
0"
b101101101001100111111101011011 #
0$
b10101101101001100111110000110110 '
b10101000 &
#338
1"
#339
b0 !
0"
b111110100000101010000101111101 #
1%
b10111110100000101001111011100101 '
b10101001 &
#340
1"
#341
0"
b111000001111001101100101110000 #
1$
b10111000001111001101011110000000 '
b10101010 &
#342
1"
#343
0"
b11010001001110101001100110100 #
0$
0%
b10011010001001110101000101110111 '
b10101011 &
#344
1"
#345
0"
b10101100100011111000001001011001 #
1$
b101100100011111000000011111010 '
b10101100 &
#346
b10101100100011111000001001011001 !
1"
#347
0"
b10011011111101001010001000110111 #
0$
b11011111101001010000111111001 '
b10101101 &
#348
1"
#349
0"
b10111001001011000110010001110010 #
b111001001011000110001100100100 '
b10101110 &
#350
1"
#351
b0 !
0"
b1010000011101100010111110100000 #
1%
b11010000011101100010110011101011 '
b10101111 &
#352
1"
#353
0"
b11010000001010100011011010100000 #
b1010000001010100011010001111110 '
b10110000 &
#354
1"
#355
0"
b11001111101011010100110010011111 #
b1001111101011010100101011001101 '
b10110001 &
#356
1"
#357
0"
b10000011000010010001100000000110 #
1$
0%
b11000010010001011110001000 '
b10110010 &
#358
b10000011000010010001100000000110 !
1"
#359
0"
b11110110101100011001100111101 #
0$
b10011110110101100011000000011111 '
b10110011 &
#360
1"
#361
0"
b10010001000101100011110000100010 #
b10001000101100011101011000010 '
b10110100 &
#362
1"
#363
b0 !
0"
b10110010001011000000111001100100 #
1%
b110010001011000000110101100001 '
b10110101 &
#364
1"
#365
0"
b1100001111110100111101111000011 #
1$
0%
b11100001111110100111100010101100 '
b10110110 &
#366
b1100001111110100111101111000011 !
1"
#367
0"
b1111111011101000011000111111110 #
b11111111011101000010111100010011 '
b10110111 &
#368
b1111111011101000011000111111110 !
1"
#369
b0 !
0"
b10011010110110111111100000110101 #
1%
b11010110110111111011111000110 '
b10111000 &
#370
1"
#371
0"
b11110101110110000001111011101011 #
b1110101110110000001110110110101 '
b10111001 &
#372
1"
#373
0"
b10111011001110101100110001110110 #
0%
b111011001110101100101010010000 '
b10111010 &
#374
b10111011001110101100110001110110 !
1"
#375
b0 !
0"
b100101010101101011111101001010 #
0$
1%
b10100101010101101011110111000111 '
b10111011 &
#376
1"
#377
0"
b11100111011100001001000011001110 #
1$
b1100111011100001000111110001010 '
b10111100 &
#378
1"
#379
0"
b11010111110101000111000010101111 #
b1010111110101000110111111001001 '
b10111101 &
#380
1"
#381
0"
b11101001011110110001001011010010 #
b1101001011110110001000100110100 '
b10111110 &
#382
1"
#383
0"
b1000111100100100011001110001111 #
b11000111100100100011000000111011 '
b10111111 &
#384
1"
#385
0"
b101101011110011110100101011010 #
b10101101011110011110011000001110 '
b11000000 &
#386
1"
#387
0"
b1101010100100111011100111010101 #
0$
0%
b11101010100100111011011110011101 '
b11000001 &
#388
1"
#389
0"
b11000110000001110001001010001100 #
b1000110000001110001000010011000 '
b11000010 &
#390
1"
#391
0"
b11101000001111001001110011010000 #
b1101000001111001001101001101111 '
b11000011 &
#392
1"
#393
0"
b10000101010100101010000000001010 #
1%
b101010100101001111101010010 '
b11000100 &
#394
1"
#395
0"
b10101110001011000110101001011100 #
1$
b101110001011000110100100110001 '
b11000101 &
#396
1"
#397
0"
b10100010101010010100111001000101 #
0$
0%
b100010101010010100110010111100 '
b11000110 &
#398
1"
#399
0"
b101011001000011101001101010110 #
b10101011001000011101000001100011 '
b11000111 &
#400
1"
#401
0"
b1101000110011100010000111010001 #
1$
b11101000110011100001111101010110 '
b11001000 &
#402
b1101000110011100010000111010001 !
1"
#403
b0 !
0"
b1101010011011001011101111010100 #
0$
1%
b11101010011011001011100010000101 '
b11001001 &
#404
1"
#405
0"
b10111000010011110000101001110000 #
b111000010011110000100110100000 '
b11001010 &
#406
1"
#407
0"
b10000001101110110100100100000 #
0%
b10010000001101110110011000010111 '
b11001011 &
#408
1"
#409
0"
b11110001101111001000110011100011 #
1$
1%
b1110001101111001000101000011010 '
b11001100 &
#410
1"
#411
0"
b1111110101011101001101111111101 #
0%
b11111110101011101001100110011001 '
b11001101 &
#412
b1111110101011101001101111111101 !
1"
#413
0"
b11001110011011000100110010011100 #
0$
b1001110011011000100101101000100 '
b11001110 &
#414
1"
#415
b0 !
0"
b10100101110100001011000001001011 #
1%
b100101110100001010111110001011 '
b11001111 &
#416
1"
#417
0"
b11111011001011101100010011110110 #
b1111011001011101100001110011110 '
b11010000 &
#418
1"
#419
0"
b11011011010111100001100110110 #
1$
b10011011011010111100000001101101 '
b11010001 &
#420
1"
#421
0"
b10011111000111111101011000111110 #
0$
0%
b11111000111111101010110101000 '
b11010010 &
#422
1"
#423
0"
b10000110100100101100001000001101 #
1%
b110100100101100000010111111 '
b11010011 &
#424
1"
#425
0"
b10001001011110100111000000010010 #
0%
b1001011110100110111111100010 '
b11010100 &
#426
1"
#427
0"
b11001100100011010001100110011 #
1$
1%
b10011001100100011010000100000001 '
b11010101 &
#428
1"
#429
0"
b111100000101110010111101111000 #
b10111100000101110010110011001100 '
b11010110 &
#430
1"
#431
0"
b110111001010000110111101101110 #
0$
b10110111001010000110110110110011 '
b11010111 &
#432
1"
#433
0"
b10011100111111011111010000111001 #
1$
b11100111111011111001011100110 '
b11011000 &
#434
1"
#435
0"
b1100011100101010111000111000111 #
b11100011100101010110111101010101 '
b11011001 &
#436
1"
#437
0"
b1111000001100101001011111110000 #
0$
b11111000001100101001010010110000 '
b11011010 &
#438
1"
#439
0"
b10110111101101100100110001101111 #
b110111101101100100101001100111 '
b11011011 &
#440
1"
#441
0"
b1010011101001000111001110100111 #
1$
0%
b11010011101001000111000010101010 '
b11011100 &
#442
b1010011101001000111001110100111 !
1"
#443
0"
b100100010010000010000101001000 #
b10100100010010000001111101101001 '
b11011101 &
#444
b100100010010000010000101001000 !
1"
#445
b0 !
0"
b11001111010010001001100110011 #
0$
1%
b10011001111010010001000101010100 '
b11011110 &
#446
1"
#447
0"
b1011101000011101010110110111010 #
b11011101000011101010101011011011 '
b11011111 &
#448
1"
#449
0"
b11111101001010011100111011111010 #
0%
b1111101001010011100110100101110 '
b11100000 &
#450
1"
#451
0"
b101111011010100110011101011110 #
b10101111011010100110010100111101 '
b11100001 &
#452
1"
#453
0"
b1011010011011000110100110110100 #
1$
1%
b11011010011011000110011010111000 '
b11100010 &
#454
1"
#455
0"
b11000101101001011010010010001011 #
b1000101101001011010001100001111 '
b11100011 &
#456
1"
#457
0"
b10000110000111101010111000001100 #
b110000111101010110001110010 '
b11100100 &
#458
1"
#459
0"
b11011000000000001011011010110000 #
b1011000000000001011010011010001 '
b11100101 &
#460
1"
#461
0"
b11110101100011010001101011101011 #
0$
b1110101100011010001100011011100 '
b11100110 &
#462
1"
#463
0"
b1111110010001010000100111111100 #
1$
0%
b11111110010001010000011100000011 '
b11100111 &
#464
b1111110010001010000100111111100 !
1"
#465
b0 !
0"
b1011101101011000111010110111011 #
0$
1%
b11011101101011000111001001110110 '
b11101000 &
#466
1"
#467
0"
b101000011001110100010101010000 #
1$
0%
b10101000011001110100001000100101 '
b11101001 &
#468
b101000011001110100010101010000 !
1"
#469
0"
b11001110010111100110110010011100 #
b1001110010111100110101111000000 '
b11101010 &
#470
b11001110010111100110110010011100 !
1"
#471
b0 !
0"
b10101010100000000110110001010101 #
1%
b101010100000000110101010110111 '
b11101011 &
#472
1"
#473
0"
b10111010000110010100010001110100 #
b111010000110010100001100111010 '
b11101100 &
#474
1"
#475
0"
b110000001001100000001101100000 #
b10110000001001100000000100111001 '
b11101101 &
#476
1"
#477
0"
b11101100100110100110010011011001 #
0$
b1101100100110100110001101100100 '
b11101110 &
#478
1"
#479
0"
b11000100111010010010010010001001 #
1$
0%
b1000100111010010010001000101011 '
b11101111 &
#480
b11000100111010010010010010001001 !
1"
#481
b0 !
0"
b11100000000011000000010011000000 #
1%
b1100000000011000000001010111110 '
b11110000 &
#482
1"
#483
0"
b11011011100001001010100010110111 #
0%
b1011011100001001010011000001101 '
b11110001 &
#484
b11011011100001001010100010110111 !
1"
#485
b0 !
0"
b1010110110001011100010110101101 #
0$
1%
b11010110110001011100001111001000 '
b11110010 &
#486
1"
#487
0"
b1001011000000100100001110010110 #
1$
0%
b11001011000000100100000101011111 '
b11110011 &
#488
b1001011000000100100001110010110 !
1"
#489
0"
b11010000100100000101011010100001 #
0$
b1010000100100000101010100000010 '
b11110100 &
#490
1"
#491
b0 !
0"
b10001000110111101010011000010001 #
1$
1%
b1000110111101010010010100001 '
b11110101 &
#492
1"
#493
0"
b1101000101000001001100011010 #
0%
b10001101000101000001000011101100 '
b11110110 &
#494
b1101000101000001001100011010 !
1"
#495
b0 !
0"
b11101000111101001001111011010001 #
0$
1%
b1101000111101001001110001010011 '
b11110111 &
#496
1"
#497
0"
b10000001110110101010000000000011 #
1$
0%
b1110110101001111000000110 '
b11111000 &
#498
b10000001110110101010000000000011 !
1"
#499
0"
b1001111101101110011001110011111 #
b11001111101101110011000011110101 '
b11111001 &
#500
b1001111101101110011001110011111 !
1"
#501
0"
b101001000010111001000101010010 #
0$
b10101001000010111000111011010000 '
b11111010 &
#502
1"
#503
0"
b1111001000000101100100111110010 #
b11111001000000101100011100000111 '
b11111011 &
#504
1"
#505
0"
b10000110110011000000001000001101 #
1$
b110110011000000000111001010 '
b11111100 &
#506
b10000110110011000000001000001101 !
1"
#507
0"
b10101101100011010100000001011011 #
b101101100011010011111100001001 '
b11111101 &
#508
b10101101100011010100000001011011 !
1"
#509
0"
b11100101111010010100001011001011 #
b1100101111010010100000101110100 '
b11111110 &
#510
b11100101111010010100001011001011 !
1"
#511
b0 !
0"
b11101010101111010001011011010101 #
0$
1%
b1101010101111010001010101111011 '
b11111111 &
#512
1"
#513
0"
b11001001001101100110011010010010 #
b1001001001101100110010001001110 '
b100000000 &
