test_designs/adffe/adffe.v


module adffe(
	input clk_i,
	input rst_i,
	input en_i,
	input [31:0] data_i,
	output reg [31:0] q_o
);
	always @(posedge clk_i or posedge rst_i) begin
		if (rst_i) begin
			q_o <= 0;
		end else if (en_i) begin
			q_o <= data_i;
		end
	end
endmodule

test_designs/adffe/adffe_tb.v
`include "adffe.v"

module tb;
	reg           clk_i;
	reg           rst_i;
	reg           en_i;
	reg [31:0]    data_i;
	wire [31:0]   q_o;

	adffe dut (
		.clk_i(clk_i),
		.rst_i(rst_i),
		.en_i(en_i),
		.data_i(data_i),
		.q_o(q_o)
	);
	integer seed;
	integer i;
	initial begin
		seed = 123;
		$dumpfile(".adffe_tb.vcd");
		$dumpvars(1, tb);
		clk_i = 0;
		rst_i = 1;
		en_i = 0;
		data_i = 0;

		#1;
		rst_i = 0;

		for (i = 0; i < 1000; i+= 1) begin
			rst_i = $random(seed);
			en_i = $random(seed);
			data_i = $random(seed);
			clk_i = 0;
			#1;
			clk_i = 1;
			#1;
		end
	end

endmodule

test_designs/adffe/.adffe_tb.vcd
$date
	Mon Nov 17 20:09:56 2025
$end
$version
	Icarus Verilog
$end
$timescale
	1s
$end
$scope module tb $end
$var wire 32 ! q_o [31:0] $end
$var reg 1 " clk_i $end
$var reg 32 # data_i [31:0] $end
$var reg 1 $ en_i $end
$var reg 1 % rst_i $end
$var integer 32 & i [31:0] $end
$var integer 32 ' seed [31:0] $end
$upscope $end
$enddefinitions $end
$comment Show the parameter values. $end
$dumpall
$end
#0
$dumpvars
b1111011 '
bx &
1%
0$
b0 #
0"
b1010 !
$end
#1
b10000000100000011010001000000001 #
b100000011010000110000000 '
1$
b0 &
1%
#2
1"
#3
0"
b11110100000011101010100111101 #
b10011110100000011101001110000001 '
b1 &
#4
1"
#5
0"
b11011001001101001110110010110010 #
b1011001001101001110101101001110 '
0%
b10 &
#6
b11011001001101001110110010110010 !
1"
#7
0"
b10001010101000010110010000010101 #
b1010101000010110001101110111 '
b11 &
#8
b10001010101000010110010000010101 !
1"
#9
b1010 !
0"
b10011000110000001011001000110001 #
b11000110000001011000101001100 '
0$
1%
b100 &
#10
1"
#11
0"
b11001100100110101101011010011001 #
b1001100100110101101010111011101 '
b101 &
#12
1"
#13
0"
b10001010101101100111110000010101 #
b1010101101100111101011111010 '
0%
b110 &
#14
1"
#15
0"
b11010011010110010010111010100110 #
b1010011010110010010110000110011 '
b111 &
#16
1"
#17
0"
b11110001110110011111110011100011 #
b1110001110110011111101111011000 '
1$
1%
b1000 &
#18
1"
#19
0"
b10111001001100001010010001110010 #
b111001001100001010001111111001 '
b1001 &
#20
1"
#21
0"
b1101000001111111111010111010000 #
b11101000001111111111001101100110 '
0%
b1010 &
#22
b1101000001111111111010111010000 !
1"
#23
0"
b10101101111110000001100001011011 #
b101101111110000001011010101111 '
b1011 &
#24
b10101101111110000001100001011011 !
1"
#25
b1010 !
0"
b11111111100000000000111011111111 #
b1111111100000000000110100100100 '
0$
1%
b1100 &
#26
1"
#27
0"
b100111010110010101101101001110 #
b10100111010110010101100111010101 '
b1101 &
#28
1"
#29
0"
b1100101111100011100001111001011 #
b11100101111100011100000010010010 '
0%
b1110 &
#30
1"
#31
0"
b10101001111100001010000001010011 #
b101001111100001001111011101011 '
b1111 &
#32
1"
#33
0"
b11101100101011000011001011011001 #
b1101100101011000011000100110000 '
1$
1%
b10000 &
#34
1"
#35
0"
b1110101100100101101010111101011 #
b11110101100100101101001101110001 '
b10001 &
#36
1"
#37
0"
b1101110110000010001000111011101 #
b11101110110000010000111001111110 '
0%
b10010 &
#38
b1101110110000010001000111011101 !
1"
#39
0"
b10001100110100110000001000011001 #
b1100110100110000000011100111 '
b10011 &
#40
b10001100110100110000001000011001 !
1"
#41
b1010 !
0"
b1111100111010100111010111111001 #
b11111100111010100111001111111100 '
0$
1%
b10100 &
#42
1"
#43
0"
b1100011100111101010111111000111 #
b11100011100111101010110011001101 '
b10101 &
#44
1"
#45
0"
b10000001101000111100101000000011 #
b1101000111100100100101010 '
0%
b10110 &
#46
1"
#47
0"
b11101010100010010011101011010101 #
b1101010100010010011100010100011 '
b10111 &
#48
1"
#49
0"
b11001011010001100000000 #
b10000000011001011010000110001000 '
1$
1%
b11000 &
#50
1"
#51
0"
b11100000111100100001100111000 #
b10011100000111100100000111101001 '
b11001 &
#52
1"
#53
0"
b1001111011111001001111110011110 #
b11001111011111001001110010010110 '
0%
b11010 &
#54
b1001111011111001001111110011110 !
1"
#55
0"
b10010111010100110000010000101110 #
b10111010100110000001000011111 '
b11011 &
#56
b10010111010100110000010000101110 !
1"
#57
b1010 !
0"
b1100110101100110100011111001101 #
b11100110101100110100010111010100 '
0$
1%
b11100 &
#58
1"
#59
0"
b10011101111011101011000000111011 #
b11101111011101010111011000101 '
b11101 &
#60
1"
#61
0"
b1000101110001101111011110001011 #
b11000101110001101111010011000010 '
0%
b11110 &
#62
1"
#63
0"
b11101111100000011101101011011111 #
b1101111100000011101100101011011 '
b11111 &
#64
1"
#65
0"
b111100010111111010111101111000 #
b10111100010111111010110011100000 '
1$
1%
b100000 &
#66
1"
#67
0"
b11100001010001001101000011000010 #
b1100001010001001100111101100001 '
b100001 &
#68
1"
#69
0"
b10110010000000101111111001100100 #
b110010000000101111110110101110 '
0%
b100010 &
#70
b10110010000000101111111001100100 !
1"
#71
0"
b10110000111101001111110001100001 #
b110000111101001111101001010111 '
b100011 &
#72
b10110000111101001111110001100001 !
1"
#73
b1010 !
0"
b11111001110011110010100111110 #
b10011111001110011110001010101100 '
0$
1%
b100100 &
#74
1"
#75
0"
b11010100100010010100000010101001 #
b1010100100010010011111110111101 '
b100101 &
#76
1"
#77
0"
b1101001111000011010010111010011 #
b11101001111000011010001101011010 '
0%
b100110 &
#78
1"
#79
0"
b11100010010101010110001011000100 #
b1100010010101010110000100010011 '
b100111 &
#80
1"
#81
0"
b11110101010111111011010011101010 #
b1110101010111111011001100111000 '
1$
1%
b101000 &
#82
1"
#83
0"
b1100111101000101110100011001 #
b10001100111101000101101111011001 '
b101001 &
#84
1"
#85
0"
b100100001100001001001101001000 #
b10100100001100001001000111000110 '
0%
b101010 &
#86
b100100001100001001001101001000 !
1"
#87
0"
b100000100011100101100001000 #
b10000100000100011100100110001111 '
b101011 &
#88
b100000100011100101100001000 !
1"
#89
b1010 !
0"
b11110011000010011010110011100110 #
b1110011000010011010101010000100 '
0$
1%
b101100 &
#90
1"
#91
0"
b11000110111010100100000010001101 #
b1000110111010100011111110110101 '
b101101 &
#92
1"
#93
0"
b1101110100001100011011111011101 #
b11101110100001100011010011110010 '
0%
b101110 &
#94
1"
#95
0"
b10000111000110101011000000001110 #
b111000110101010111111001011 '
b101111 &
#96
1"
#97
0"
b111011000101110001011101110110 #
b10111011000101110001010010010000 '
1$
1%
b110000 &
#98
1"
#99
0"
b10010010000101101100100000100100 #
b10010000101101100011101010001 '
b110001 &
#100
1"
#101
0"
b11101011101011011011101011010111 #
b1101011101011011011100011011110 '
0%
b110010 &
#102
b11101011101011011011101011010111 !
1"
#103
0"
b1000101010111100101000110001010 #
b11000101010111100100111111000111 '
b110011 &
#104
b1000101010111100101000110001010 !
1"
#105
b1010 !
0"
b10100110010110011111111001001100 #
b100110010110011111110101011100 '
0$
1%
b110100 &
#106
1"
#107
0"
b11000101010010011001000010001010 #
b1000101010010011000111010101101 '
b110101 &
#108
1"
#109
0"
b1000110110100110000101110001101 #
b11000110110100110000100110001010 '
0%
b110110 &
#110
1"
#111
0"
b1111000000001001010011111110000 #
b11111000000001001010010110000011 '
b110111 &
#112
1"
#113
0"
b11111101101000110011001011111011 #
b1111101101000110011000011101000 '
1$
1%
b111000 &
#114
1"
#115
0"
b10010110000100011111001000101100 #
b10110000100011111000111001001 '
b111001 &
#116
1"
#117
0"
b111011011101101010100001110 #
b10000111011011101101001011110110 '
0%
b111010 &
#118
b111011011101101010100001110 !
1"
#119
0"
b1100111011010110110111111001110 #
b11100111011010110110110011111111 '
b111011 &
#120
b1100111011010110110111111001110 !
1"
#121
b1010 !
0"
b10110010100011100011110001100101 #
b110010100011100011101100110100 '
0$
1%
b111100 &
#122
1"
#123
0"
b1110000000110110000111111100000 #
b11110000000110110000110010100101 '
b111101 &
#124
1"
#125
0"
b110001111100101000001101100011 #
b10110001111100101000000100100010 '
0%
b111110 &
#126
1"
#127
0"
b11010000111000100010010010100001 #
b1010000111000100010001000111011 '
b111111 &
#128
1"
#129
0"
b11100011000011010110101011000110 #
b1100011000011010110100001000000 '
1$
1%
b1000000 &
#130
1"
#131
0"
b11101000010001111011110011010000 #
b1101000010001111011101101000001 '
b1000001 &
#132
1"
#133
0"
b1100001001101000100001111000010 #
b11100001001101000100000000001110 '
0%
b1000010 &
#134
b1100001001101000100001111000010 !
1"
#135
0"
b10111110001001100000001001111100 #
b111110001001100000000100110111 '
b1000011 &
#136
b10111110001001100000001001111100 !
1"
#137
b1010 !
0"
b110011101101011100011101100111 #
b10110011101101011100010000001100 '
0$
1%
b1000100 &
#138
1"
#139
0"
b1100111100011101001101111001111 #
b11100111100011101001100110011101 '
b1000101 &
#140
1"
#141
0"
b11000100100110101111110010001001 #
b1000100100110101111101110111010 '
0%
b1000110 &
#142
1"
#143
0"
b1001010100111100000011110010101 #
b11001010100111100000010111110011 '
b1000111 &
#144
1"
#145
0"
b11001100110010110001110010011001 #
b1001100110010110001101010011000 '
1$
1%
b1001000 &
#146
1"
#147
0"
b1101001100101100000010111010011 #
b11101001100101100000001110111001 '
b1001001 &
#148
1"
#149
0"
b101111000010100110001101011110 #
b10101111000010100110000000100110 '
0%
b1001010 &
#150
b101111000010100110001101011110 !
1"
#151
0"
b10010010010101101110111000100100 #
b10010010101101110110001101111 '
b1001011 &
#152
b10010010010101101110111000100100 !
1"
#153
b1010 !
0"
b10000110000010111111100000001100 #
b110000010111111011111100100 '
0$
1%
b1001100 &
#154
1"
#155
0"
b11101011000100000001011011010110 #
b1101011000100000001010110010101 '
b1001101 &
#156
1"
#157
0"
b100010100011101101101101000101 #
b10100010100011101101100101010010 '
0%
b1001110 &
#158
1"
#159
0"
b11000110101111110011001010001101 #
b1000110101111110011000010101011 '
b1001111 &
#160
1"
#161
0"
b1101001111011010100100011010 #
b10001101001111011010011111110000 '
1$
1%
b1010000 &
#162
1"
#163
0"
b1100011110101101010110111000111 #
b11100011110101101010101100110001 '
b1010001 &
#164
1"
#165
0"
b10000100110010011001010000001001 #
b100110010011001001100111110 '
0%
b1010010 &
#166
b10000100110010011001010000001001 !
1"
#167
0"
b100101001000110001000101001010 #
b10100101001000110000111010100111 '
b1010011 &
#168
b100101001000110001000101001010 !
1"
#169
b1010 !
0"
b10010011011110000011100000100110 #
b10011011110000011011010111100 '
0$
1%
b1010100 &
#170
1"
#171
0"
b1101000110001110110001111010001 #
b11101000110001110110000010001101 '
b1010101 &
#172
1"
#173
0"
b1101000000111000111101111010000 #
b11101000000111000111100111101010 '
0%
b1010110 &
#174
1"
#175
0"
b1001010111010001000010110010101 #
b11001010111010001000001001100011 '
b1010111 &
#176
1"
#177
0"
b1001101001100100111001110011010 #
b11001101001100100111000001001000 '
1$
1%
b1011000 &
#178
1"
#179
0"
b11010001010111111001001010100010 #
b1010001010111111001000110101001 '
b1011001 &
#180
1"
#181
0"
b10101100101100011101100101011 #
b10010101100101100011100101010110 '
0%
b1011010 &
#182
b10101100101100011101100101011 !
1"
#183
0"
b100011100010110100100101000111 #
b10100011100010110100011111011111 '
b1011011 &
#184
b100011100010110100100101000111 !
1"
#185
b1010 !
0"
b11010001000011011110001010100010 #
b1010001000011011110000010010100 '
0$
1%
b1011100 &
#186
1"
#187
0"
b11111101000110000101110011111010 #
b1111101000110000101101010000101 '
b1011101 &
#188
1"
#189
0"
b1000011100111100011111110000111 #
b11000011100111100011110110000010 '
0%
b1011110 &
#190
1"
#191
0"
b1101100010110001101110111011000 #
b11101100010110001101101100011011 '
b1011111 &
#192
1"
#193
0"
b100001011000101101010101000010 #
b10100001011000101101001110100000 '
1$
1%
b1100000 &
#194
1"
#195
0"
b10010100100000101001100000101001 #
b10100100000101001011100100001 '
b1100001 &
#196
1"
#197
0"
b100101011000001011010101001010 #
b10100101011000001011001001101110 '
0%
b1100010 &
#198
b100101011000001011010101001010 !
1"
#199
0"
b10001001111011000111101000010011 #
b1001111011000111100000010111 '
b1100011 &
#200
b10001001111011000111101000010011 !
1"
#201
b1010 !
0"
b11101100100011000101011011011001 #
b1101100100011000101010101101100 '
0$
1%
b1100100 &
#202
1"
#203
0"
b11100010001000101110010011000100 #
b1100010001000101110001101111101 '
b1100101 &
#204
1"
#205
0"
b10111110111110101000011001111101 #
b111110111110101000010000011010 '
0%
b1100110 &
#206
1"
#207
0"
b101011011010110001110101010110 #
b10101011011010110001101011010011 '
b1100111 &
#208
1"
#209
0"
b1001111111101000011001110011111 #
b11001111111101000011000111111000 '
1$
1%
b1101000 &
#210
1"
#211
0"
b10011111000011011001110000111110 #
b11111000011011001101110011001 '
b1101001 &
#212
1"
#213
0"
b10101010011001010110000001010100 #
b101010011001010101111010000110 '
0%
b1101010 &
#214
b10101010011001010110000001010100 !
1"
#215
0"
b11110111011111111000000011101110 #
b1110111011111110111111101001111 '
b1101011 &
#216
b11110111011111111000000011101110 !
1"
#217
b1010 !
0"
b101001110111101111011101010011 #
b10101001110111101111010101000100 '
0$
1%
b1101100 &
#218
1"
#219
0"
b11001111010000101101110010011110 #
b1001111010000101101101101110101 '
b1101101 &
#220
1"
#221
0"
b111001001000111010111101110010 #
b10111001001000111010110110110010 '
0%
b1101110 &
#222
1"
#223
0"
b111111000101100010001101111110 #
b10111111000101100010000110001011 '
b1101111 &
#224
1"
#225
0"
b11000101111101111110110010001011 #
b1000101111101111110101101010000 '
1$
1%
b1110000 &
#226
1"
#227
0"
b1001110010101000000100010011 #
b10001001110010100111111100010001 '
b1110001 &
#228
1"
#229
0"
b10011110101011001001111000111101 #
b11110101011001001110110011110 '
0%
b1110010 &
#230
b10011110101011001001111000111101 !
1"
#231
0"
b1110001110110010011111111100011 #
b11110001110110010011110110000111 '
b1110011 &
#232
b1110001110110010011111111100011 !
1"
#233
b1010 !
0"
b1110000100111010010001111100001 #
b11110000100111010010000000011100 '
0$
1%
b1110100 &
#234
1"
#235
0"
b1001000100100000010010110010001 #
b11001000100100000010001001101101 '
b1110101 &
#236
1"
#237
0"
b10001111100110000001110000011111 #
b1111100110000001101001001010 '
0%
b1110110 &
#238
1"
#239
0"
b11010000011011001101000010100000 #
b1010000011011001100111101000011 '
b1110111 &
#240
1"
#241
0"
b111100111010110110000101111001 #
b10111100111010110101111110101000 '
1$
1%
b1111000 &
#242
1"
#243
0"
b11011111111110010001100110111 #
b10011011111111110010000110001001 '
b1111001 &
#244
1"
#245
0"
b10000001100010101101000000000011 #
b1100010101100111110110110 '
0%
b1111010 &
#246
b10000001100010101101000000000011 !
1"
#247
0"
b10011000011010101001010000110000 #
b11000011010101001001010111111 '
b1111011 &
#248
b10011000011010101001010000110000 !
1"
#249
b1010 !
0"
b1001100010100011011100010011 #
b10001001100010100011010111110100 '
0$
1%
b1111100 &
#250
1"
#251
0"
b11011110010111101001101010111100 #
b1011110010111101001100001100101 '
b1111101 &
#252
1"
#253
0"
b1110111111000100010101111101111 #
b11110111111000100010100111100010 '
0%
b1111110 &
#254
1"
#255
0"
b10100110000111100000010001001100 #
b100110000111100000001111111011 '
b1111111 &
#256
1"
#257
0"
b10010000001101111111000000100000 #
b10000001101111110111100000000 '
1$
1%
b10000000 &
#258
1"
#259
0"
b1000010111011010110010110000101 #
b11000010111011010110001100000001 '
b10000001 &
#260
1"
#261
0"
b1001001000000101011100010010 #
b10001001001000000101010011001110 '
0%
b10000010 &
#262
b1001001000000101011100010010 !
1"
#263
0"
b1001000000000000110000110010000 #
b11001000000000000101111011110111 '
b10000011 &
#264
b1001000000000000110000110010000 !
1"
#265
b1010 !
0"
b1100000101011001100100011000 #
b10001100000101011001011011001100 '
0$
1%
b10000100 &
#266
1"
#267
0"
b1011100101111100001111110111001 #
b11011100101111100001110101011101 '
b10000101 &
#268
1"
#269
0"
b1001000110000011111100010010 #
b10001001000110000011110001111010 '
0%
b10000110 &
#270
1"
#271
0"
b10111111111101001010000001111111 #
b111111111101001001111110110011 '
b10000111 &
#272
1"
#273
0"
b11000010101100101111101010000101 #
b1000010101100101111100101011000 '
1$
1%
b10001000 &
#274
1"
#275
0"
b11111001010100110010010011110010 #
b1111001010100110010001101111001 '
b10001001 &
#276
1"
#277
0"
b11110110011000111100000111 #
b10000011110110011000110011100110 '
0%
b10001010 &
#278
b11110110011000111100000111 !
1"
#279
0"
b10101110010000111000010001011100 #
b101110010000111000001000101111 '
b10001011 &
#280
b10101110010000111000010001011100 !
1"
#281
b1010 !
0"
b1111011110110101010010111110111 #
b11111011110110101010001010100100 '
0$
1%
b10001100 &
#282
1"
#283
0"
b11101010111110101001001011010101 #
b1101010111110101001000101010101 '
b10001101 &
#284
1"
#285
0"
b1110101010111001011010111101010 #
b11110101010111001011001000010010 '
0%
b10001110 &
#286
1"
#287
0"
b1100010010101111000010111000100 #
b11100010010101111000001001101011 '
b10001111 &
#288
1"
#289
0"
b10110100000111011110000001101000 #
b110100000111011101111010110000 '
1$
1%
b10010000 &
#290
1"
#291
0"
b10011110111010100100010000111101 #
b11110111010100100001011110001 '
b10010001 &
#292
1"
#293
0"
b1101001111011101101100111010011 #
b11101001111011101101011111111110 '
0%
b10010010 &
#294
b1101001111011101101100111010011 !
1"
#295
0"
b11001101001110001101111010011010 #
b1001101001110001101110001100111 '
b10010011 &
#296
b11001101001110001101111010011010 !
1"
#297
b1010 !
0"
b10110001000001011101100101100 #
b10010110001000001011100101111100 '
0$
1%
b10010100 &
#298
1"
#299
0"
b11011000110111101011100110110 #
b10011011000110111101010001001101 '
b10010101 &
#300
1"
#301
0"
b11110011010111011110110011100110 #
b1110011010111011110101010101010 '
0%
b10010110 &
#302
1"
#303
0"
b10010001110010011000111000100011 #
b10001110010011000110000100011 '
b10010111 &
#304
1"
#305
0"
b10000110101001100000000000001101 #
b110101001011111111100001000 '
1$
1%
b10011000 &
#306
1"
#307
0"
b111111111010001010001101111111 #
b10111111111010001010000101101001 '
b10011001 &
#308
1"
#309
0"
b10011110111001001001100000111101 #
b11110111001001001011000010110 '
0%
b10011010 &
#310
b10011110111001001001100000111101 !
1"
#311
0"
b1101110110000010100111111011101 #
b11101110110000010100110110011111 '
b10011011 &
#312
b1101110110000010100111111011101 !
1"
#313
b1010 !
0"
b11001111010110110011110010011110 #
b1001111010110110011101101010100 '
0$
1%
b10011100 &
#314
1"
#315
0"
b11101001011001011100100011010010 #
b1101001011001011100011001000101 '
b10011101 &
#316
1"
#317
0"
b11010111110101100100100010101111 #
b1010111110101100100011001000010 '
0%
b10011110 &
#318
1"
#319
0"
b11111110011010011001111011111100 #
b1111110011010011001110011011011 '
b10011111 &
#320
1"
#321
0"
b10110100011001001011110001101000 #
b110100011001001011101001100000 '
1$
1%
b10100000 &
#322
1"
#323
0"
b1001100100000000010000110011001 #
b11001100100000000001111011100001 '
b10100001 &
#324
1"
#325
0"
b11100011000010110010100011000110 #
b1100011000010110010011100101110 '
0%
b10100010 &
#326
b11100011000010110010100011000110 !
1"
#327
0"
b10001000000110011011011000010000 #
b1000000110011011010111010111 '
b10100011 &
#328
b10001000000110011011011000010000 !
1"
#329
b1010 !
0"
b101010011000101100000001 #
b10000000101010011000100000101100 '
0$
1%
b10100100 &
#330
1"
#331
0"
b10101011110110000100100001010111 #
b101011110110000100011100111101 '
b10100101 &
#332
1"
#333
0"
b11011111000011000010011010111110 #
b1011111000011000010010011011010 '
0%
b10100110 &
#334
1"
#335
0"
b1011111011100101001011110111110 #
b11011111011100101001010010010011 '
b10100111 &
#336
1"
#337
0"
b11010100110111110111001010101001 #
b1010100110111110111000010111000 '
1$
1%
b10101000 &
#338
1"
#339
0"
b1000000010111101001110110000000 #
b11000000010111101001101101011001 '
b10101001 &
#340
1"
#341
0"
b11110100111111101110110011101001 #
b1110100111111101110101101000110 '
0%
b10101010 &
#342
b11110100111111101110110011101001 !
1"
#343
0"
b1101010110101111011100011010 #
b10001101010110101111010100001111 '
b10101011 &
#344
b1101010110101111011100011010 !
1"
#345
b1010 !
0"
b1000101010101110000001110001010 #
b11000101010101110000000000000100 '
0$
1%
b10101100 &
#346
1"
#347
0"
b11110001101011110011100011100011 #
b1110001101011110011011100110101 '
b10101101 &
#348
1"
#349
0"
b10100110010100011110100001001100 #
b100110010100011110011001110010 '
0%
b10101110 &
#350
1"
#351
0"
b111110101110110101010101111101 #
b10111110101110110101001101001011 '
b10101111 &
#352
1"
#353
0"
b10010100001111000010100100101 #
b10010010100001111000001000010000 '
1$
1%
b10110000 &
#354
1"
#355
0"
b111010001011011111100101110100 #
b10111010001011011111011011010001 '
b10110001 &
#356
1"
#357
0"
b11100011001010000100010011000110 #
b1100011001010000100001001011110 '
0%
b10110010 &
#358
b11100011001010000100010011000110 !
1"
#359
0"
b110100111110011110110101101001 #
b10110100111110011110101101000111 '
b10110011 &
#360
b110100111110011110110101101001 !
1"
#361
b1010 !
0"
b1000010110110000010100010000 #
b10001000010110110000001011011100 '
0$
1%
b10110100 &
#362
1"
#363
0"
b1010010111000100111100110100101 #
b11010010111000100111011000101101 '
b10110101 &
#364
1"
#365
0"
b1010101100001011110110110101011 #
b11010101100001011110101100001010 '
0%
b10110110 &
#366
1"
#367
0"
b110100001101101011101101101000 #
b10110100001101101011100100000011 '
b10110111 &
#368
1"
#369
0"
b1010000001110100101000110100000 #
b11010000001110100100111001101000 '
1$
1%
b10111000 &
#370
1"
#371
0"
b10000011000101000001001000000110 #
b11000101000001000101001001 '
b10111001 &
#372
1"
#373
0"
b1101001110111000111100011010 #
b10001101001110111000110001110110 '
0%
b10111010 &
#374
b1101001110111000111100011010 !
1"
#375
0"
b101011010001110111101101010110 #
b10101011010001110111100001111111 '
b10111011 &
#376
b101011010001110111101101010110 !
1"
#377
b1010 !
0"
b11000001110110001111001010000011 #
b1000001110110001111000010110100 '
0$
1%
b10111100 &
#378
1"
#379
0"
b101111101001011110011101011111 #
b10101111101001011110010000100101 '
b10111101 &
#380
1"
#381
0"
b1111000100100101001010111110001 #
b11111000100100101001001010100010 '
0%
b10111110 &
#382
1"
#383
0"
b10010001011100111010011000100010 #
b10001011100111010010110111011 '
b10111111 &
#384
1"
#385
0"
b11111110110000010011011011111101 #
b1111110110000010011010111000000 '
1$
1%
b11000000 &
#386
1"
#387
0"
b110001100101100110100001100 #
b10000110001100101100101011000001 '
b11000001 &
#388
1"
#389
0"
b1010101101110010010101110101011 #
b11010101101110010010100110001110 '
0%
b11000010 &
#390
b1010101101110010010101110101011 !
1"
#391
0"
b110101111100000111111101101011 #
b10110101111100000111110010110111 '
b11000011 &
#392
b110101111100000111111101101011 !
1"
#393
b1010 !
0"
b11100100101000000010101011001001 #
b1100100101000000010100110001100 '
0$
1%
b11000100 &
#394
1"
#395
0"
b1011111111010010110001110111111 #
b11011111111010010110000100011101 '
b11000101 &
#396
1"
#397
0"
b1000111011100011111100010001 #
b10001000111011100011110100111010 '
0%
b11000110 &
#398
1"
#399
0"
b1111101000111001111101111111010 #
b11111101000111001111100101110011 '
b11000111 &
#400
1"
#401
0"
b10100010010100011001101001000100 #
b100010010100011001100000011000 '
1$
1%
b11001000 &
#402
1"
#403
0"
b10111000001010000000010001110000 #
b111000001010000000001100111001 '
b11001001 &
#404
1"
#405
0"
b10000011011011010111101000000110 #
b11011011010111100110100110 '
0%
b11001010 &
#406
b10000011011011010111101000000110 !
1"
#407
0"
b1000111011111011101100110001110 #
b11000111011111011101011111101111 '
b11001011 &
#408
b1000111011111011101100110001110 !
1"
#409
b1010 !
0"
b1111011101011000000111111110111 #
b11111011101011000000110101100100 '
0$
1%
b11001100 &
#410
1"
#411
0"
b11010010110110001100111010100101 #
b1010010110110001100110100010101 '
b11001101 &
#412
1"
#413
0"
b10100111000110110100110001001110 #
b100111000110110100101011010010 '
0%
b11001110 &
#414
1"
#415
0"
b1111110011110011001011111111100 #
b11111110011110011001010000101011 '
b11001111 &
#416
1"
#417
0"
b1000000011001101011100010000 #
b10001000000011001101010101110000 '
1$
1%
b11010000 &
#418
1"
#419
0"
b11101110100011011001110011011101 #
b1101110100011011001101010110001 '
b11010001 &
#420
1"
#421
0"
b11010010111100001101111010100101 #
b1010010111100001101110010111110 '
0%
b11010010 &
#422
b11010010111100001101111010100101 !
1"
#423
0"
b10110101000110110100000101 #
b10000010110101000110101000100111 '
b11010011 &
#424
b10110101000110110100000101 !
1"
#425
b1010 !
0"
b1110111101000111111111111101111 #
b11110111101000111111110000111100 '
0$
1%
b11010100 &
#426
1"
#427
0"
b11110010111000000101100111100 #
b10011110010111000000100000001101 '
b11010101 &
#428
1"
#429
0"
b100001010000001110100001000 #
b10000100001010000001101101101010 '
0%
b11010110 &
#430
1"
#431
0"
b1111000111011000101011111110001 #
b11111000111011000101010111100011 '
b11010111 &
#432
1"
#433
0"
b101011100000000100111101010111 #
b10101011100000000100110111001000 '
1$
1%
b11011000 &
#434
1"
#435
0"
b10100111011110010111001001001110 #
b100111011110010111000100101001 '
b11011001 &
#436
1"
#437
0"
b10111000001001111011010001110000 #
b111000001001111011001011010110 '
0%
b11011010 &
#438
b10111000001001111011010001110000 !
1"
#439
0"
b101110101101010001010101011101 #
b10101110101101010001001101011111 '
b11011011 &
#440
b101110101101010001010101011101 !
1"
#441
b1010 !
0"
b10101100010110110101100001011000 #
b101100010110110101011000010100 '
0$
1%
b11011100 &
#442
1"
#443
0"
b11111110100101101111010011111101 #
b1111110100101101111001000000101 '
b11011101 &
#444
1"
#445
0"
b1111011001011110001000111110110 #
b11111011001011110000111100000010 '
0%
b11011110 &
#446
1"
#447
0"
b10111011101000010000100101110 #
b10010111011101000001111010011011 '
b11011111 &
#448
1"
#449
0"
b11001100001001010110001010011000 #
b1001100001001010110000100100000 '
1$
1%
b11100000 &
#450
1"
#451
0"
b11000000111111010110100010000001 #
b1000000111111010110011010100001 '
b11100001 &
#452
1"
#453
0"
b11001111110000100101110010011111 #
b1001111110000100101101111101110 '
0%
b11100010 &
#454
b11001111110000100101110010011111 !
1"
#455
0"
b10011001001111001011010000110010 #
b11001001111001011001110010111 '
b11100011 &
#456
b10011001001111001011010000110010 !
1"
#457
b1010 !
0"
b1111110010100010111110111111100 #
b11111110010100010111101011101100 '
0$
1%
b11100100 &
#458
1"
#459
0"
b11000101011010010110110010001010 #
b1000101011010010110101011111101 '
b11100101 &
#460
1"
#461
0"
b11011010110101101000011010110101 #
b1011010110101101000010110011010 '
0%
b11100110 &
#462
1"
#463
0"
b10101000001010111101000001010000 #
b101000001010111100111001010011 '
b11100111 &
#464
1"
#465
0"
b10110010111000010111000001100101 #
b110010111000010110111101111000 '
1$
1%
b11101000 &
#466
1"
#467
0"
b100000101001110101110101000001 #
b10100000101001110101101100011001 '
b11101001 &
#468
1"
#469
0"
b101111010011101100000001 #
b10000000101111010011100000000110 '
0%
b11101010 &
#470
b101111010011101100000001 !
1"
#471
0"
b1101011011001000010110111010110 #
b11101011011001000010101011001111 '
b11101011 &
#472
b1101011011001000010110111010110 !
1"
#473
b1010 !
0"
b1000000001100011100110110000000 #
b11000000001100011100101011000100 '
0$
1%
b11101100 &
#474
1"
#475
0"
b10111001111011110101010001110011 #
b111001111011110101001011110101 '
b11101101 &
#476
1"
#477
0"
b1011110110100001110000110111101 #
b11011110110100001101111100110010 '
0%
b11101110 &
#478
1"
#479
0"
b1100111110010100100011111001111 #
b11100111110010100100010100001011 '
b11101111 &
#480
1"
#481
0"
b10100111100001011101101001001111 #
b100111100001011101100011010000 '
1$
1%
b11110000 &
#482
1"
#483
0"
b11001011000000010011000010010110 #
b1001011000000010010111010010001 '
b11110001 &
#484
1"
#485
0"
b11001101111000001010100010011011 #
b1001101111000001010011100011110 '
0%
b11110010 &
#486
b11001101111000001010100010011011 !
1"
#487
0"
b11101100100000000101101011011001 #
b1101100100000000101100100000111 '
b11110011 &
#488
b11101100100000000101101011011001 !
1"
#489
b1010 !
0"
b1000000010100111010011110000000 #
b11000000010100111010010110011100 '
0$
1%
b11110100 &
#490
1"
#491
0"
b1101000000000001000101111010000 #
b11101000000000001000100111101101 '
b11110101 &
#492
1"
#493
0"
b11011001010111000111110010110010 #
b1011001010111000111101111001010 '
0%
b11110110 &
#494
1"
#495
0"
b111101001000100110010101111010 #
b10111101001000100110001011000011 '
b11110111 &
#496
1"
#497
0"
b10110010011111111111100101100 #
b10010110010011111111110100101000 '
1$
1%
b11111000 &
#498
1"
#499
0"
b11101011000100001100001011010110 #
b1101011000100001100000100001001 '
b11111001 &
#500
1"
#501
0"
b11010111010000010000101010101110 #
b1010111010000010000100100110110 '
0%
b11111010 &
#502
b11010111010000010000101010101110 !
1"
#503
0"
b10110101110000100010000001101011 #
b110101110000100001111000111111 '
b11111011 &
#504
b10110101110000100010000001101011 !
1"
#505
b1010 !
0"
b10000110001110100110110000001100 #
b110001110100110101101110100 '
0$
1%
b11111100 &
#506
1"
#507
0"
b11011111101100001111000010111111 #
b1011111101100001110111111100101 '
b11111101 &
#508
1"
#509
0"
b1100110000111011110100011001 #
b10001100110000111011101101100010 '
0%
b11111110 &
#510
1"
#511
0"
b11100100101000110000100011001001 #
b1100100101000110000011101111011 '
b11111111 &
#512
1"
#513
0"
b1100101011010010011111111001010 #
b11100101011010010011110010000000 '
1$
1%
b100000000 &
#514
1"
#515
0"
b11001001110101111111010010010011 #
b1001001110101111111001010000001 '
b100000001 &
#516
1"
#517
0"
b10001011101111101100000000010111 #
b1011101111101011111001001110 '
0%
b100000010 &
