test_designs/pmux/pmux.v


module pmux(
	input [2:0]     sel_i,
	input [15:0] data_0_i,
	input [15:0] data_1_i,
	input [15:0] data_2_i,
	input [15:0] data_3_i,
	input [15:0] data_4_i,
	input [15:0] data_5_i,
	input [15:0] data_6_i,
	input [15:0] data_7_i,
	output reg [15:0]   q_o
);
	always @(*) begin
		case (sel_i)
			3'b000: q_o = data_0_i;
			3'b001: q_o = data_1_i;
			3'b010: q_o = data_2_i;
			3'b011: q_o = data_3_i;
			3'b100: q_o = data_4_i;
			3'b101: q_o = data_5_i;
			3'b110: q_o = data_6_i;
			3'b111: q_o = data_7_i;
		endcase
	end
endmodule

test_designs/pmux/pmux_tb.v
`include "pmux.v"

module tb;
	reg [2:0]     sel_i;
	reg [15:0] data_0_i;
	reg [15:0] data_1_i;
	reg [15:0] data_2_i;
	reg [15:0] data_3_i;
	reg [15:0] data_4_i;
	reg [15:0] data_5_i;
	reg [15:0] data_6_i;
	reg [15:0] data_7_i;
	wire [15:0]   q_o;

	pmux dut (
		.sel_i(sel_i),
		.data_0_i(data_0_i),
		.data_1_i(data_1_i),
		.data_2_i(data_2_i),
		.data_3_i(data_3_i),
		.data_4_i(data_4_i),
		.data_5_i(data_5_i),
		.data_6_i(data_6_i),
		.data_7_i(data_7_i),
		.q_o(q_o)
	);
	integer seed;
	integer i;
	initial begin
		seed = 123;
		$dumpfile(".pmux_tb.vcd");
		$dumpvars(0, tb);

		for (i = 0; i < 1000; i+= 1) begin
			sel_i = $random(seed);
			data_0_i = $random(seed);
			data_1_i = $random(seed);
			data_2_i = $random(seed);
			data_3_i = $random(seed);
			data_4_i = $random(seed);
			data_5_i = $random(seed);
			data_6_i = $random(seed);
			data_7_i = $random(seed);
			#1;
		end
	end

endmodule

test_designs/pmux/.pmux_tb.vcd
$date
	Mon Jan 19 13:27:16 2026
$end
$version
	Icarus Verilog
$end
$timescale
	1s
$end
$scope module tb $end
$var wire 16 ! q_o [15:0] $end
$var reg 16 " data_0_i [15:0] $end
$var reg 16 # data_1_i [15:0] $end
$var reg 16 $ data_2_i [15:0] $end
$var reg 16 % data_3_i [15:0] $end
$var reg 16 & data_4_i [15:0] $end
$var reg 16 ' data_5_i [15:0] $end
$var reg 16 ( data_6_i [15:0] $end
$var reg 16 ) data_7_i [15:0] $end
$var reg 3 * sel_i [2:0] $end
$var integer 32 + i [31:0] $end
$var integer 32 , seed [31:0] $end
$scope module dut $end
$var wire 16 - data_0_i [15:0] $end
$var wire 16 . data_1_i [15:0] $end
$var wire 16 / data_2_i [15:0] $end
$var wire 16 0 data_3_i [15:0] $end
$var wire 16 1 data_4_i [15:0] $end
$var wire 16 2 data_5_i [15:0] $end
$var wire 16 3 data_6_i [15:0] $end
$var wire 16 4 data_7_i [15:0] $end
$var wire 3 5 sel_i [2:0] $end
$var reg 16 6 q_o [15:0] $end
$upscope $end
$upscope $end
$enddefinitions $end
$comment Show the parameter values. $end
$dumpall
$end
#0
$dumpvars
b1110110010110010 6
b1 5
b1111110011100011 4
b10111010100110 3
b111110000010101 2
b1101011010011001 1
b1011001000110001 0
b110010000010101 /
b1110110010110010 .
b1101010100111101 -
b1110001110110011111101111011000 ,
b0 +
b1 *
b1111110011100011 )
b10111010100110 (
b111110000010101 '
b1101011010011001 &
b1011001000110001 %
b110010000010101 $
b1110110010110010 #
b1101010100111101 "
b1110110010110010 !
$end
#1
b111011111111 !
b111011111111 6
b1101010111101011 )
b1101010111101011 4
b11001011011001 (
b11001011011001 3
b1010000001010011 '
b1010000001010011 2
b1100001111001011 &
b1100001111001011 1
b101101101001110 %
b101101101001110 0
b111011111111 $
b111011111111 /
b1100001011011 #
b1100001011011 .
b1111010111010000 "
b1111010111010000 -
b10 *
b10 5
b11110101100100101101001101110001 ,
b1 +
#2
b1010001100000000 !
b1010001100000000 6
b1001111110011110 )
b1001111110011110 4
b100001100111000 (
b100001100111000 3
b1010001100000000 '
b1010001100000000 2
b11101011010101 &
b11101011010101 1
b1100101000000011 %
b1100101000000011 0
b1010111111000111 $
b1010111111000111 /
b111010111111001 #
b111010111111001 .
b1000011001 "
b1000011001 -
b101 *
b101 5
b11001111011111001001110010010110 ,
b10 +
#3
b1111111001100100 !
b1111111001100100 6
b1111110001100001 )
b1111110001100001 4
b1111111001100100 (
b1111111001100100 3
b1101000011000010 '
b1101000011000010 2
b1010111101111000 &
b1010111101111000 1
b1101101011011111 %
b1101101011011111 0
b1111011110001011 $
b1111011110001011 /
b1011000000111011 #
b1011000000111011 .
b100011111001101 "
b100011111001101 -
b110 *
b110 5
b110000111101001111101001010111 ,
b11 +
#4
b1100101100001000 !
b1100101100001000 6
b1010110011100110 )
b1010110011100110 4
b1100101100001000 (
b1100101100001000 3
b1001001101001000 '
b1001001101001000 2
b101110100011001 &
b101110100011001 1
b1011010011101010 %
b1011010011101010 0
b110001011000100 $
b110001011000100 /
b1010010111010011 #
b1010010111010011 .
b100000010101001 "
b100000010101001 -
b1110011000010011010101010000100 ,
b100 +
#5
b101000110001010 !
b101000110001010 6
b1001000010001010 )
b1001000010001010 4
b1111111001001100 (
b1111111001001100 3
b101000110001010 '
b101000110001010 2
b1011101011010111 &
b1011101011010111 1
b1100100000100100 %
b1100100000100100 0
b1011101110110 $
b1011101110110 /
b1011000000001110 #
b1011000000001110 .
b11011111011101 "
b11011111011101 -
b101 *
b101 5
b1000101010010011000111010101101 ,
b101 +
#6
b11110001100101 !
b11110001100101 6
b1000001101100011 )
b1000001101100011 4
b111111100000 (
b111111100000 3
b11110001100101 '
b11110001100101 2
b110111111001110 &
b110111111001110 1
b1101010100001110 %
b1101010100001110 0
b1111001000101100 $
b1111001000101100 /
b11001011111011 #
b11001011111011 .
b1010011111110000 "
b1010011111110000 -
b10110001111100101000000100100010 ,
b110 +
#7
b1011110011010000 !
b1011110011010000 6
b11110010101 )
b11110010101 4
b1111110010001001 (
b1111110010001001 3
b1001101111001111 '
b1001101111001111 2
b1100011101100111 &
b1100011101100111 1
b1001111100 %
b1001111100 0
b100001111000010 $
b100001111000010 /
b1011110011010000 #
b1011110011010000 .
b110101011000110 "
b110101011000110 -
b1 *
b1 5
b11001010100111100000010111110011 ,
b111 +
#8
b110001101011110 !
b110001101011110 6
b1010100100011010 )
b1010100100011010 4
b11001010001101 (
b11001010001101 3
b1101101101000101 '
b1101101101000101 2
b1011011010110 &
b1011011010110 1
b1111100000001100 %
b1111100000001100 0
b1110111000100100 $
b1110111000100100 /
b110001101011110 #
b110001101011110 .
b10111010011 "
b10111010011 -
b10001101001111011010011111110000 ,
b1000 +
#9
b1001001010100010 !
b1001001010100010 6
b1001001010100010 )
b1001001010100010 4
b111001110011010 (
b111001110011010 3
b1000010110010101 '
b1000010110010101 2
b111101111010000 &
b111101111010000 1
b110001111010001 %
b110001111010001 0
b11100000100110 $
b11100000100110 /
b1000101001010 #
b1000101001010 .
b1001010000001001 "
b1001010000001001 -
b111 *
b111 5
b1010001010111111001000110101001 ,
b1001 +
#10
b11111110000111 !
b11111110000111 6
b1011010101001010 )
b1011010101001010 4
b1001100000101001 (
b1001100000101001 3
b1101010101000010 '
b1101010101000010 2
b1101110111011000 &
b1101110111011000 1
b11111110000111 %
b11111110000111 0
b101110011111010 $
b101110011111010 /
b1110001010100010 #
b1110001010100010 .
b100100101000111 "
b100100101000111 -
b11 *
b11 5
b10100101011000001011001001101110 ,
b1010 +
#11
b1110101010110 !
b1110101010110 6
b1000000011101110 )
b1000000011101110 4
b110000001010100 (
b110000001010100 3
b1001110000111110 '
b1001110000111110 2
b11001110011111 &
b11001110011111 1
b1110101010110 %
b1110101010110 0
b1000011001111101 $
b1000011001111101 /
b1110010011000100 #
b1110010011000100 .
b101011011011001 "
b101011011011001 -
b1110111011111110111111101001111 ,
b1011 +
#12
b1110110010001011 !
b1110110010001011 6
b10001111100001 )
b10001111100001 4
b11111111100011 (
b11111111100011 3
b1001111000111101 '
b1001111000111101 2
b1000000100010011 &
b1000000100010011 1
b1110110010001011 %
b1110110010001011 0
b10001101111110 $
b10001101111110 /
b1010111101110010 #
b1010111101110010 .
b1101110010011110 "
b1101110010011110 -
b11110000100111010010000000011100 ,
b1100 +
#13
b1101000010100000 !
b1101000010100000 6
b1001101010111100 )
b1001101010111100 4
b11011100010011 (
b11011100010011 3
b1001010000110000 '
b1001010000110000 2
b1101000000000011 &
b1101000000000011 1
b10001100110111 %
b10001100110111 0
b110000101111001 $
b110000101111001 /
b1101000010100000 #
b1101000010100000 .
b1110000011111 "
b1110000011111 -
b1 *
b1 5
b1011110010111101001100001100101 ,
b1101 +
#14
b11111100010010 !
b11111100010010 6
b11111100010010 )
b11111100010010 4
b1111110111001 (
b1111110111001 3
b1001100100011000 '
b1001100100011000 2
b110000110010000 &
b110000110010000 1
b101011100010010 %
b101011100010010 0
b110010110000101 $
b110010110000101 /
b1111000000100000 #
b1111000000100000 .
b10001001100 "
b10001001100 -
b111 *
b111 5
b10001001000110000011110001111010 ,
b1110 +
#15
b1000010111000100 !
b1000010111000100 6
b1000010111000100 )
b1000010111000100 4
b1011010111101010 (
b1011010111101010 3
b1001001011010101 '
b1001001011010101 2
b1010010111110111 &
b1010010111110111 1
b1000010001011100 %
b1000010001011100 0
b1000111100000111 $
b1000111100000111 /
b10010011110010 #
b10010011110010 .
b1111101010000101 "
b1111101010000101 -
b11100010010101111000001001101011 ,
b1111 +
#16
b100010000111101 !
b100010000111101 6
b1101 )
b1101 4
b1000111000100011 (
b1000111000100011 3
b1110110011100110 '
b1110110011100110 2
b1101011100110110 &
b1101011100110110 1
b1011101100101100 %
b1011101100101100 0
b1101111010011010 $
b1101111010011010 /
b1101100111010011 #
b1101100111010011 .
b100010000111101 "
b100010000111101 -
b0 *
b0 5
b110101001011111111100001000 ,
b10000 +
#17
b10000110011001 !
b10000110011001 6
b10000110011001 )
b10000110011001 4
b1011110001101000 (
b1011110001101000 3
b1001111011111100 '
b1001111011111100 2
b100100010101111 &
b100100010101111 1
b1100100011010010 %
b1100100011010010 0
b11110010011110 $
b11110010011110 /
b100111111011101 #
b100111111011101 .
b1001100000111101 "
b1001100000111101 -
b111 *
b111 5
b11001100100000000001111011100001 ,
b10001 +
#18
b1001110110000000 !
b1001110110000000 6
b1110110011101001 )
b1110110011101001 4
b1001110110000000 (
b1001110110000000 3
b111001010101001 '
b111001010101001 2
b1001011110111110 &
b1001011110111110 1
b10011010111110 %
b10011010111110 0
b100100001010111 $
b100100001010111 /
b1000101100000001 #
b1000101100000001 .
b1011011000010000 "
b1011011000010000 -
b110 *
b110 5
b1110100111111101110101101000110 ,
b10010 +
#19
b1110100001001100 !
b1110100001001100 6
b1110110101101001 )
b1110110101101001 4
b100010011000110 (
b100010011000110 3
b1111100101110100 '
b1111100101110100 2
b1000010100100101 &
b1000010100100101 1
b101010101111101 %
b101010101111101 0
b1110100001001100 $
b1110100001001100 /
b11100011100011 #
b11100011100011 .
b1110001010 "
b1110001010 -
b10 *
b10 5
b10110100111110011110101101000111 ,
b10011 +
#20
b111100110100101 !
b111100110100101 6
b1111001010000011 )
b1111001010000011 4
b111101101010110 (
b111101101010110 3
b1000111100011010 '
b1000111100011010 2
b1001000000110 &
b1001000000110 1
b101000110100000 %
b101000110100000 0
b1011101101101000 $
b1011101101101000 /
b1110110110101011 #
b1110110110101011 .
b111100110100101 "
b111100110100101 -
b0 *
b0 5
b1000001110110001111000010110100 ,
b10100 +
#21
b110001110111111 !
b110001110111111 6
b110001110111111 )
b110001110111111 4
b10101011001001 (
b10101011001001 3
b111111101101011 '
b111111101101011 2
b10101110101011 &
b10101110101011 1
b1100110100001100 %
b1100110100001100 0
b11011011111101 $
b11011011111101 /
b1010011000100010 #
b1010011000100010 .
b1001010111110001 "
b1001010111110001 -
b111 *
b111 5
b11011111111010010110000100011101 ,
b10101 +
#22
b1001101001000100 !
b1001101001000100 6
b100110001001110 )
b100110001001110 4
b1100111010100101 (
b1100111010100101 3
b111111110111 '
b111111110111 2
b1101100110001110 &
b1101100110001110 1
b111101000000110 %
b111101000000110 0
b10001110000 $
b10001110000 /
b1001101001000100 #
b1001101001000100 .
b1111101111111010 "
b1111101111111010 -
b1 *
b1 5
b100111000110110100101011010010 ,
b10110 +
#23
b1111111111101111 !
b1111111111101111 6
b101011111110001 )
b101011111110001 4
b1110100001000 (
b1110100001000 3
b101100111100 '
b101100111100 2
b1111111111101111 &
b1111111111101111 1
b110110100000101 %
b110110100000101 0
b1101111010100101 $
b1101111010100101 /
b1001110011011101 #
b1001110011011101 .
b1101011100010000 "
b1101011100010000 -
b100 *
b100 5
b11111000111011000101010111100011 ,
b10111 +
#24
b110001010011000 !
b110001010011000 6
b110001010011000 )
b110001010011000 4
b10000100101110 (
b10000100101110 3
b1000111110110 '
b1000111110110 2
b1111010011111101 &
b1111010011111101 1
b101100001011000 %
b101100001011000 0
b1010101011101 $
b1010101011101 /
b1011010001110000 #
b1011010001110000 .
b111001001001110 "
b111001001001110 -
b111 *
b111 5
b1001100001001010110000100100000 ,
b11000 +
#25
b1011010000110010 !
b1011010000110010 6
b101110101000001 )
b101110101000001 4
b111000001100101 (
b111000001100101 3
b1101000001010000 '
b1101000001010000 2
b1000011010110101 &
b1000011010110101 1
b110110010001010 %
b110110010001010 0
b111110111111100 $
b111110111111100 /
b1011010000110010 #
b1011010000110010 .
b101110010011111 "
b101110010011111 -
b1 *
b1 5
b10100000101001110101101100011001 ,
b11001 +
#26
b1100110110000000 !
b1100110110000000 6
b1010100010011011 )
b1010100010011011 4
b11000010010110 (
b11000010010110 3
b1101101001001111 '
b1101101001001111 2
b100011111001111 &
b100011111001111 1
b1110000110111101 %
b1110000110111101 0
b101010001110011 $
b101010001110011 /
b1100110110000000 #
b1100110110000000 .
b10110111010110 "
b10110111010110 -
b1001101111000001010011100011110 ,
b11010 +
#27
b1000101111010000 !
b1000101111010000 6
b10000001101011 )
b10000001101011 4
b101010101110 (
b101010101110 3
b1100001011010110 '
b1100001011010110 2
b1111111100101100 &
b1111111100101100 1
b110010101111010 %
b110010101111010 0
b111110010110010 $
b111110010110010 /
b1000101111010000 #
b1000101111010000 .
b1010011110000000 "
b1010011110000000 -
b110101110000100001111000111111 ,
b11011 +
#28
b1111010010010011 !
b1111010010010011 6
b111111110000000 )
b111111110000000 4
b101110110101011 (
b101110110101011 3
b1100000000010111 '
b1100000000010111 2
b1111010010010011 &
b1111010010010011 1
b11111111001010 %
b11111111001010 0
b100011001001 $
b100011001001 /
b1011110100011001 #
b1011110100011001 .
b1111000010111111 "
b1111000010111111 -
b100 *
b100 5
b11000000000101010111110001001100 ,
b11100 +
#29
b1010000010111 !
b1010000010111 6
b1100101100011100 )
b1100101100011100 4
b11101011000000 (
b11101011000000 3
b1110111111000111 '
b1110111111000111 2
b10100100010101 &
b10100100010101 1
b1010010001101011 %
b1010010001101011 0
b1111100011110100 $
b1111100011110100 /
b1010000010111 #
b1010000010111 .
b1111111101101001 "
b1111111101101001 -
b1 *
b1 5
b10001110011010101100100011010101 ,
b11101 +
#30
b1000111011011111 !
b1000111011011111 6
b111101110110 )
b111101110110 4
b1111110010101100 (
b1111110010101100 3
b11010101 '
b11010101 2
b1011100100000111 &
b1011100100000111 1
b1010001101101001 %
b1010001101101001 0
b1011010010110101 $
b1011010010110101 /
b1000111011011111 #
b1000111011011111 .
b110011010111001 "
b110011010111001 -
b10111011001110110000110000101010 ,
b11110 +
#31
b11001111100101 !
b11001111100101 6
b110001011010010 )
b110001011010010 4
b1001100111001100 (
b1001100111001100 3
b1101111000110000 '
b1101111000110000 2
b11001111100101 &
b11001111100101 1
b1001101010110010 %
b1001101010110010 0
b1001000011011100 $
b1001000011011100 /
b1100001111 #
b1100001111 .
b101111111110101 "
b101111111110101 -
b100 *
b100 5
b1101001001110000110000001011011 ,
b11111 +
#32
b1100101011011110 !
b1100101011011110 6
b11000010110001 )
b11000010110001 4
b1100101011011110 (
b1100101011011110 3
b1010100000000110 '
b1010100000000110 2
b101000000000101 &
b101000000000101 1
b10111110010000 %
b10111110010000 0
b111001111010110 $
b111001111010110 /
b101001000100000 #
b101001000100000 .
b111000111010011 "
b111000111010011 -
b110 *
b110 5
b1011000101110100010111000111000 ,
b100000 +
#33
b10100101001000 !
b10100101001000 6
b10100101001000 )
b10100101001000 4
b1111000010010111 (
b1111000010010111 3
b1111100110111000 '
b1111100110111000 2
b1001100010010110 &
b1001100010010110 1
b11000111100111 %
b11000111100111 0
b101011010101010 $
b101011010101010 /
b10001011101110 #
b10001011101110 .
b100011000010100 "
b100011000010100 -
b111 *
b111 5
b10100100000001000010011001010001 ,
b100001 +
#34
b100011010011000 !
b100011010011000 6
b100011010011000 )
b100011010011000 4
b11001101100111 (
b11001101100111 3
b110110101011011 '
b110110101011011 2
b1100111110001001 &
b1100111110001001 1
b1100111100110111 %
b1100111100110111 0
b101111010010111 $
b101111010010111 /
b101001010110 #
b101001010110 .
b1000100001101100 "
b1000100001101100 -
b1001100010110110100010111110110 ,
b100010 +
#35
b10101001100010 !
b10101001100010 6
b1111101101101010 )
b1111101101101010 4
b1010001011111 (
b1010001011111 3
b1101110011001011 '
b1101110011001011 2
b10001110101 &
b10001110101 1
b10101001100010 %
b10101001100010 0
b1010011010011010 $
b1010011010011010 /
b1011110101010100 #
b1011110101010100 .
b1010100010000010 "
b1010100010000010 -
b11 *
b11 5
b10110101000100011111100000110111 ,
b100011 +
#36
b1110111001101011 !
b1110111001101011 6
b10010010001000 )
b10010010001000 4
b1100010010010001 (
b1100010010010001 3
b1001010001101011 '
b1001010001101011 2
b10010000100 &
b10010000100 1
b1011100110011 %
b1011100110011 0
b1110111001101011 $
b1110111001101011 /
b1000000001111011 #
b1000000001111011 .
b10101100111110 "
b10101100111110 -
b10 *
b10 5
b1000100010101110010001011100100 ,
b100100 +
#37
b10100100100 !
b10100100100 6
b1011000111001101 )
b1011000111001101 4
b1100001111000100 (
b1100001111000100 3
b1100011010011011 '
b1100011010011011 2
b10100010000111 &
b10100010000111 1
b1000110001010101 %
b1000110001010101 0
b10100100100 $
b10100100100 /
b1111100011111110 #
b1111100011111110 .
b1011111000010100 "
b1011111000010100 -
b11100110100111111010111110001101 ,
b100101 +
#38
b101001101000001 !
b101001101000001 6
b1110001000100100 )
b1110001000100100 4
b1000101010100101 (
b1000101010100101 3
b1100110011011010 '
b1100110011011010 2
b1110000001000111 &
b1110000001000111 1
b10111000011011 %
b10111000011011 0
b101001101000001 $
b101001101000001 /
b10110111100100 #
b10110111100100 .
b10101010011101 "
b10101010011101 -
b10010010000101110000010000010 ,
b100110 +
#39
b11000010010 !
b11000010010 6
b1000001010111101 )
b1000001010111101 4
b1000100111010001 (
b1000100111010001 3
b1111010011101110 '
b1111010011101110 2
b1010001100000010 &
b1010001100000010 1
b1111000111010110 %
b1111000111010110 0
b11000010010 $
b11000010010 /
b11100111111100 #
b11100111111100 .
b1111000001001001 "
b1111000001001001 -
b1011110101100111000000111010011 ,
b100111 +
#40
b1101100110101101 !
b1101100110101101 6
b1100100000001011 )
b1100100000001011 4
b110101111111010 (
b110101111111010 3
b1001100101001 '
b1001100101001 2
b1100110101010101 &
b1100110101010101 1
b1010001111111110 %
b1010001111111110 0
b1101100110101101 $
b1101100110101101 /
b1001100011101 #
b1001100011101 .
b1110100111010 "
b1110100111010 -
b101110011101100011001010000 ,
b101000 +
#41
b111011111011111 !
b111011111011111 6
b110001011111001 )
b110001011111001 4
b1001110011101011 (
b1001110011101011 3
b1111100111001010 '
b1111100111001010 2
b1101111010111011 &
b1101111010111011 1
b1111001000000011 %
b1111001000000011 0
b10110000110111 $
b10110000110111 /
b111011111011111 #
b111011111011111 .
b1011001001010010 "
b1011001001010010 -
b1 *
b1 5
b1111100110000010110000010001001 ,
b101001 +
#42
b100100100010110 !
b100100100010110 6
b10100000001110 )
b10100000001110 4
b1000010111100010 (
b1000010111100010 3
b1000110001101100 '
b1000110001101100 2
b110010010011 &
b110010010011 1
b100111100100101 %
b100111100100101 0
b100100100010110 $
b100100100010110 /
b1010001000111100 #
b1010001000111100 .
b1010101010010001 "
b1010101010010001 -
b10 *
b10 5
b111000100000010011111001110 ,
b101010 +
#43
b1000100000001010 !
b1000100000001010 6
b101101011111000 )
b101101011111000 4
b1100000111000100 (
b1100000111000100 3
b10010111011001 '
b10010111011001 2
b1111011100011101 &
b1111011100011101 1
b1000100000001010 %
b1000100000001010 0
b1100000000101000 $
b1100000000101000 /
b1010111100000101 #
b1010111100000101 .
b110001110010101 "
b110001110010101 -
b11 *
b11 5
b1111100011111110101100100101111 ,
b101011 +
#44
b110110111101001 !
b110110111101001 6
b100011000100001 )
b100011000100001 4
b1001010100111100 (
b1001010100111100 3
b110110111101001 '
b110110111101001 2
b10001111001100 &
b10001111001100 1
b11101010101011 %
b11101010101011 0
b100101101001111 $
b100101101001111 /
b1001011000011010 #
b1001011000011010 .
b1011011111 "
b1011011111 -
b101 *
b101 5
b10000110011100100010001111100 ,
b101100 +
#45
b10100001001110 !
b10100001001110 6
b1111011000010010 )
b1111011000010010 4
b10100001001110 (
b10100001001110 3
b1110011000001001 '
b1110011000001001 2
b1000101001000110 &
b1000101001000110 1
b110001111100011 %
b110001111100011 0
b1011110010100011 $
b1011110010100011 /
b11010111100010 #
b11010111100010 .
b10111110111110 "
b10111110111110 -
b110 *
b110 5
b1001000000001111010101000101 ,
b101101 +
#46
b101100011101101 !
b101100011101101 6
b10100010111000 )
b10100010111000 4
b101100011101101 (
b101100011101101 3
b1101010100011000 '
b1101010100011000 2
b10111010001111 &
b10111010001111 1
b111110010111111 %
b111110010111111 0
b1011111011101101 $
b1011111011101101 /
b1101011010100110 #
b1101011010100110 .
b10010101111011 "
b10010101111011 -
b1011100000010100010011111011010 ,
b101110 +
#47
b1110110111101101 !
b1110110111101101 6
b1001110011011001 )
b1001110011011001 4
b100101101000111 (
b100101101000111 3
b10100001010110 '
b10100001010110 2
b1010110111110001 &
b1010110111110001 1
b100111011100000 %
b100111011100000 0
b1010000010010100 $
b1010000010010100 /
b1110110110001 #
b1110110110001 .
b1110110111101101 "
b1110110111101101 -
b0 *
b0 5
b1101100111100011001101001001011 ,
b101111 +
#48
b101011000000101 !
b101011000000101 6
b1000101000011001 )
b1000101000011001 4
b1110001111110000 (
b1110001111110000 3
b1011000000111111 '
b1011000000111111 2
b100011110011011 &
b100011110011011 1
b111101001010 %
b111101001010 0
b10010001101101 $
b10010001101101 /
b101011000000101 #
b101011000000101 .
b101011000011011 "
b101011000011011 -
b1 *
b1 5
b1100101110011000100101101000 ,
b110000 +
#49
b1001010101111011 !
b1001010101111011 6
b1110101110001001 )
b1110101110001001 4
b1101001010011011 (
b1101001010011011 3
b1010111001111101 '
b1010111001111101 2
b1011011011101011 &
b1011011011101011 1
b1001010101111011 %
b1001010101111011 0
b101110100001110 $
b101110100001110 /
b1001000101111000 #
b1001000101111000 .
b1010101 "
b1010101 -
b11 *
b11 5
b11000100100001011110100111000001 ,
b110001 +
#50
b1100001111010001 !
b1100001111010001 6
b1010111001011000 )
b1010111001011000 4
b10100001010 (
b10100001010 3
b1001010001010001 '
b1001010001010001 2
b1110001110000101 &
b1110001110000101 1
b1100001111010001 %
b1100001111010001 0
b1111001110000110 $
b1111001110000110 /
b1111011001111110 #
b1111011001111110 .
b111010101010011 "
b111010101010011 -
b101100011011001010110010100110 ,
b110010 +
#51
b11101101101100 !
b11101101101100 6
b10001111100110 )
b10001111100110 4
b111000011111001 (
b111000011111001 3
b111101010101011 '
b111101010101011 2
b11001111000010 &
b11001111000010 1
b101110110101110 %
b101110110101110 0
b10111100100100 $
b10111100100100 /
b11111101011001 #
b11111101011001 .
b11101101101100 "
b11101101101100 -
b0 *
b0 5
b11110011011111000010000100100111 ,
b110011 +
#52
b1111111100110110 !
b1111111100110110 6
b100001011010100 )
b100001011010100 4
b1010110101100001 (
b1010110101100001 3
b1010011011110111 '
b1010011011110111 2
b11001101110110 &
b11001101110110 1
b101100101111 %
b101100101111 0
b1111111100110110 $
b1111111100110110 /
b110000110011011 #
b110000110011011 .
b101100110111111 "
b101100110111111 -
b10 *
b10 5
b1101010010101110100000100010100 ,
b110100 +
#53
b1100011000010110 !
b1100011000010110 6
b111101100101010 )
b111101100101010 4
b1100011000010110 (
b1100011000010110 3
b10110111011100 '
b10110111011100 2
b1011000111110000 &
b1011000111110000 1
b11000010101 %
b11000010101 0
b111111111000011 $
b111111111000011 /
b1010011011001000 #
b1010011011001000 .
b1011010110011101 "
b1011010110011101 -
b110 *
b110 5
b10010101010000110111100111111101 ,
b110101 +
#54
b1000001011010000 !
b1000001011010000 6
b100010001000001 )
b100010001000001 4
b100001000000000 (
b100001000000000 3
b111011001111000 '
b111011001111000 2
b1000001011010000 &
b1000001011010000 1
b1110110001110100 %
b1110110001110100 0
b1101110100100100 $
b1101110100100100 /
b1110110000011001 #
b1110110000011001 .
b11011100111010 "
b11011100111010 -
b100 *
b100 5
b100000111101000100001000110010 ,
b110110 +
#55
b1011110010101100 !
b1011110010101100 6
b1000101100101110 )
b1000101100101110 4
b100000001000101 (
b100000001000101 3
b101101001100110 '
b101101001100110 2
b1011001100110011 &
b1011001100110011 1
b1001001011010011 %
b1001001011010011 0
b1011110010101100 $
b1011110010101100 /
b1000111101011011 #
b1000111101011011 .
b1011010000101101 "
b1011010000101101 -
b10 *
b10 5
b10010111001000101000100111000011 ,
b110111 +
#56
b11011111111101 !
b11011111111101 6
b1101100101110000 )
b1101100101110000 4
b1000011000101 (
b1000011000101 3
b1110000110011111 '
b1110000110011111 2
b1010000101111101 &
b1010000101111101 1
b1101100001001110 %
b1101100001001110 0
b11011111111101 $
b11011111111101 /
b111111101011011 #
b111111101011011 .
b1110011110 "
b1110011110 -
b10111000001111001101011110000000 ,
b111000 +
#57
b1111001111101100 !
b1111001111101100 6
b1010001000110111 )
b1010001000110111 4
b1111001111101100 (
b1111001111101100 3
b1111110011110010 '
b1111110011110010 2
b1000001001011001 &
b1000001001011001 1
b1111010110101001 %
b1111010110101001 0
b100100110000100 $
b100100110000100 /
b101001100110100 #
b101001100110100 .
b1001001101000010 "
b1001001101000010 -
b110 *
b110 5
b11011111101001010000111111001 ,
b111001 +
#58
b11100011011001 !
b11100011011001 6
b11011010100000 )
b11011010100000 4
b1001001000000000 (
b1001001000000000 3
b1110100000110111 '
b1110100000110111 2
b10111110100000 &
b10111110100000 1
b1000100101000100 %
b1000100101000100 0
b11100011011001 $
b11100011011001 /
b110010001110010 #
b110010001110010 .
b1100011001001100 "
b1100011001001100 -
b10 *
b10 5
b1010000001010100011010001111110 ,
b111010 +
#59
b1100000111111000 !
b1100000111111000 6
b11001100111101 )
b11001100111101 4
b1000010101001000 (
b1000010101001000 3
b1100000111111000 '
b1100000111111000 2
b1100000000110 &
b1100000000110 1
b1000100110001011 %
b1000100110001011 0
b101000111001010 $
b101000111001010 /
b100110010011111 #
b100110010011111 .
b1000101000111100 "
b1000101000111100 -
b101 *
b101 5
b10011110110101100011000000011111 ,
b111011 +
#60
b111001100100 !
b111001100100 6
b111101111000011 )
b111101111000011 4
b1110101100011001 (
b1110101100011001 3
b1010010011101110 '
b1010010011101110 2
b111001100100 &
b111001100100 1
b1110010011001100 %
b1110010011001100 0
b1110100000010101 $
b1110100000010101 /
b11110000100010 #
b11110000100010 .
b111000110010 "
b111000110010 -
b100 *
b100 5
b11100001111110100111100010101100 ,
b111100 +
#61
b1111100000110101 !
b1111100000110101 6
b1111011101011 )
b1111011101011 4
b1100001011 (
b1100001011 3
b111100101001011 '
b111100101001011 2
b1111100000110101 &
b1111100000110101 1
b101101101110011 %
b101101101110011 0
b1010101101001011 $
b1010101101001011 /
b11000111111110 #
b11000111111110 .
b1010101111011111 "
b1010101111011111 -
b1110101110110000001110110110101 ,
b111101 +
#62
b1000011001101001 !
b1000011001101001 6
b1001000011001110 )
b1001000011001110 4
b10111011101101 (
b10111011101101 3
b1010100010111 '
b1010100010111 2
b1011111101001010 &
b1011111101001010 1
b1110000111101110 %
b1110000111101110 0
b1000011001101001 $
b1000011001101001 /
b1100110001110110 #
b1100110001110110 .
b11111011111111 "
b11111011111111 -
b10 *
b10 5
b1100111011100001000111110001010 ,
b111110 +
#63
b11001110001111 !
b11001110001111 6
b11001110001111 )
b11001110001111 4
b1100100001110001 (
b1100100001110001 3
b110110110010001 '
b110110110010001 2
b1001011010010 &
b1001011010010 1
b1001110011001011 %
b1001110011001011 0
b1011101100011101 $
b1011101100011101 /
b111000010101111 #
b111000010101111 .
b1010100111000101 "
b1010100111000101 -
b111 *
b111 5
b11000111100100100011000000111011 ,
b111111 +
#64
b1110100101011010 !
b1110100101011010 6
b1001010001100 )
b1001010001100 4
b1101010111100100 (
b1101010111100100 3
b1000100000 '
b1000100000 2
b1011100111010101 &
b1011100111010101 1
b101110100101010 %
b101110100101010 0
b1111000000000010 $
b1111000000000010 /
b1110100101011010 #
b1110100101011010 .
b1111101011000001 "
b1111101011000001 -
b1 *
b1 5
b1000110000001110001000010011000 ,
b1000000 +
#65
b1100100110011010 !
b1100100110011010 6
b110101001011100 )
b110101001011100 4
b101111101010111 (
b101111101010111 3
b1100000000101001 '
b1100000000101001 2
b1010000000001010 &
b1010000000001010 1
b1111010110110110 %
b1111010110110110 0
b100111001001101 $
b100111001001101 /
b1001110011010000 #
b1001110011010000 .
b1100100110011010 "
b1100100110011010 -
b0 *
b0 5
b101110001011000110100100110001 ,
b1000001 +
