test_designs/swizzle_pmux/pmux.v
module pmux(
	input [1:0] sel,
	input [31:0] data_i,
	output reg [31:0] q_o
);
	always @* begin
		case (sel[1:0])
			2'h3: q_o = {24'hFFFFFF, data_i[31:24]};
			2'h2: q_o = {24'hFFFFFF, data_i[23:16]};
			2'h1: q_o = {24'hFFFFFF, data_i[15:8]};
			2'h0: q_o = {24'hFFFFFF, data_i[7:0]};
		endcase
	end
endmodule

test_designs/swizzle_pmux/pmux_tb.v
`include "pmux.v"

module tb;
	reg [1:0] sel;
	reg signed [31:0] data_i;
	wire signed [31:0] q_o;


	pmux dut (
		.sel(sel),
		.data_i(data_i),
		.q_o(q_o)
	);
	integer seed;
	integer i;
	initial begin
		seed = 123;
		$dumpfile(".pmux_tb.vcd");
		$dumpvars(0, tb);

		for (i = 0; i < 2_000; i+= 1) begin
			sel = i & 2'b11;
			data_i = $random(seed);
			#1;
		end
	end

endmodule

test_designs/swizzle_pmux/.pmux_tb.vcd
$date
	Sat Nov 22 00:04:10 2025
$end
$version
	Icarus Verilog
$end
$timescale
	1s
$end
$scope module tb $end
$var wire 32 ! q_o [31:0] $end
$var reg 32 " data_i [31:0] $end
$var reg 2 # sel [1:0] $end
$var integer 32 $ i [31:0] $end
$var integer 32 % seed [31:0] $end
$scope module dut $end
$var wire 32 & data_i [31:0] $end
$var wire 2 ' sel [1:0] $end
$var reg 32 ( q_o [31:0] $end
$upscope $end
$upscope $end
$enddefinitions $end
$comment Show the parameter values. $end
$dumpall
$end
#0
$dumpvars
b11111111111111111111111100000001 (
b0 '
b10000000100000011010001000000001 &
b100000011010000110000000 %
b0 $
b0 #
b10000000100000011010001000000001 "
b11111111111111111111111100000001 !
$end
#1
b11111111111111111111111111010101 !
b11111111111111111111111111010101 (
b11110100000011101010100111101 "
b11110100000011101010100111101 &
b10011110100000011101001110000001 %
b1 #
b1 '
b1 $
#2
b11111111111111111111111100110100 !
b11111111111111111111111100110100 (
b11011001001101001110110010110010 "
b11011001001101001110110010110010 &
b1011001001101001110101101001110 %
b10 #
b10 '
b10 $
#3
b11111111111111111111111110001010 !
b11111111111111111111111110001010 (
b10001010101000010110010000010101 "
b10001010101000010110010000010101 &
b1010101000010110001101110111 %
b11 #
b11 '
b11 $
#4
b11111111111111111111111100110001 !
b11111111111111111111111100110001 (
b10011000110000001011001000110001 "
b10011000110000001011001000110001 &
b11000110000001011000101001100 %
b0 #
b0 '
b100 $
#5
b11111111111111111111111111010110 !
b11111111111111111111111111010110 (
b11001100100110101101011010011001 "
b11001100100110101101011010011001 &
b1001100100110101101010111011101 %
b1 #
b1 '
b101 $
#6
b11111111111111111111111110110110 !
b11111111111111111111111110110110 (
b10001010101101100111110000010101 "
b10001010101101100111110000010101 &
b1010101101100111101011111010 %
b10 #
b10 '
b110 $
#7
b11111111111111111111111111010011 !
b11111111111111111111111111010011 (
b11010011010110010010111010100110 "
b11010011010110010010111010100110 &
b1010011010110010010110000110011 %
b11 #
b11 '
b111 $
#8
b11111111111111111111111111100011 !
b11111111111111111111111111100011 (
b11110001110110011111110011100011 "
b11110001110110011111110011100011 &
b1110001110110011111101111011000 %
b0 #
b0 '
b1000 $
#9
b11111111111111111111111110100100 !
b11111111111111111111111110100100 (
b10111001001100001010010001110010 "
b10111001001100001010010001110010 &
b111001001100001010001111111001 %
b1 #
b1 '
b1001 $
#10
b11111111111111111111111100111111 !
b11111111111111111111111100111111 (
b1101000001111111111010111010000 "
b1101000001111111111010111010000 &
b11101000001111111111001101100110 %
b10 #
b10 '
b1010 $
#11
b11111111111111111111111110101101 !
b11111111111111111111111110101101 (
b10101101111110000001100001011011 "
b10101101111110000001100001011011 &
b101101111110000001011010101111 %
b11 #
b11 '
b1011 $
#12
b11111111111111111111111111111111 !
b11111111111111111111111111111111 (
b11111111100000000000111011111111 "
b11111111100000000000111011111111 &
b1111111100000000000110100100100 %
b0 #
b0 '
b1100 $
#13
b11111111111111111111111101011011 !
b11111111111111111111111101011011 (
b100111010110010101101101001110 "
b100111010110010101101101001110 &
b10100111010110010101100111010101 %
b1 #
b1 '
b1101 $
#14
b11111111111111111111111111110001 !
b11111111111111111111111111110001 (
b1100101111100011100001111001011 "
b1100101111100011100001111001011 &
b11100101111100011100000010010010 %
b10 #
b10 '
b1110 $
#15
b11111111111111111111111110101001 !
b11111111111111111111111110101001 (
b10101001111100001010000001010011 "
b10101001111100001010000001010011 &
b101001111100001001111011101011 %
b11 #
b11 '
b1111 $
#16
b11111111111111111111111111011001 !
b11111111111111111111111111011001 (
b11101100101011000011001011011001 "
b11101100101011000011001011011001 &
b1101100101011000011000100110000 %
b0 #
b0 '
b10000 $
#17
b11111111111111111111111111010101 !
b11111111111111111111111111010101 (
b1110101100100101101010111101011 "
b1110101100100101101010111101011 &
b11110101100100101101001101110001 %
b1 #
b1 '
b10001 $
#18
b11111111111111111111111111000001 !
b11111111111111111111111111000001 (
b1101110110000010001000111011101 "
b1101110110000010001000111011101 &
b11101110110000010000111001111110 %
b10 #
b10 '
b10010 $
#19
b11111111111111111111111110001100 !
b11111111111111111111111110001100 (
b10001100110100110000001000011001 "
b10001100110100110000001000011001 &
b1100110100110000000011100111 %
b11 #
b11 '
b10011 $
#20
b11111111111111111111111111111001 !
b11111111111111111111111111111001 (
b1111100111010100111010111111001 "
b1111100111010100111010111111001 &
b11111100111010100111001111111100 %
b0 #
b0 '
b10100 $
#21
b11111111111111111111111110101111 !
b11111111111111111111111110101111 (
b1100011100111101010111111000111 "
b1100011100111101010111111000111 &
b11100011100111101010110011001101 %
b1 #
b1 '
b10101 $
#22
b11111111111111111111111110100011 !
b11111111111111111111111110100011 (
b10000001101000111100101000000011 "
b10000001101000111100101000000011 &
b1101000111100100100101010 %
b10 #
b10 '
b10110 $
#23
b11111111111111111111111111101010 !
b11111111111111111111111111101010 (
b11101010100010010011101011010101 "
b11101010100010010011101011010101 &
b1101010100010010011100010100011 %
b11 #
b11 '
b10111 $
#24
b11111111111111111111111100000000 !
b11111111111111111111111100000000 (
b11001011010001100000000 "
b11001011010001100000000 &
b10000000011001011010000110001000 %
b0 #
b0 '
b11000 $
#25
b11111111111111111111111101000011 !
b11111111111111111111111101000011 (
b11100000111100100001100111000 "
b11100000111100100001100111000 &
b10011100000111100100000111101001 %
b1 #
b1 '
b11001 $
#26
b11111111111111111111111101111100 !
b11111111111111111111111101111100 (
b1001111011111001001111110011110 "
b1001111011111001001111110011110 &
b11001111011111001001110010010110 %
b10 #
b10 '
b11010 $
#27
b11111111111111111111111110010111 !
b11111111111111111111111110010111 (
b10010111010100110000010000101110 "
b10010111010100110000010000101110 &
b10111010100110000001000011111 %
b11 #
b11 '
b11011 $
#28
b11111111111111111111111111001101 !
b11111111111111111111111111001101 (
b1100110101100110100011111001101 "
b1100110101100110100011111001101 &
b11100110101100110100010111010100 %
b0 #
b0 '
b11100 $
#29
b11111111111111111111111110110000 !
b11111111111111111111111110110000 (
b10011101111011101011000000111011 "
b10011101111011101011000000111011 &
b11101111011101010111011000101 %
b1 #
b1 '
b11101 $
#30
b11111111111111111111111111000110 !
b11111111111111111111111111000110 (
b1000101110001101111011110001011 "
b1000101110001101111011110001011 &
b11000101110001101111010011000010 %
b10 #
b10 '
b11110 $
#31
b11111111111111111111111111101111 !
b11111111111111111111111111101111 (
b11101111100000011101101011011111 "
b11101111100000011101101011011111 &
b1101111100000011101100101011011 %
b11 #
b11 '
b11111 $
#32
b11111111111111111111111101111000 !
b11111111111111111111111101111000 (
b111100010111111010111101111000 "
b111100010111111010111101111000 &
b10111100010111111010110011100000 %
b0 #
b0 '
b100000 $
#33
b11111111111111111111111111010000 !
b11111111111111111111111111010000 (
b11100001010001001101000011000010 "
b11100001010001001101000011000010 &
b1100001010001001100111101100001 %
b1 #
b1 '
b100001 $
#34
b11111111111111111111111100000010 !
b11111111111111111111111100000010 (
b10110010000000101111111001100100 "
b10110010000000101111111001100100 &
b110010000000101111110110101110 %
b10 #
b10 '
b100010 $
#35
b11111111111111111111111110110000 !
b11111111111111111111111110110000 (
b10110000111101001111110001100001 "
b10110000111101001111110001100001 &
b110000111101001111101001010111 %
b11 #
b11 '
b100011 $
#36
b11111111111111111111111100111110 !
b11111111111111111111111100111110 (
b11111001110011110010100111110 "
b11111001110011110010100111110 &
b10011111001110011110001010101100 %
b0 #
b0 '
b100100 $
#37
b11111111111111111111111101000000 !
b11111111111111111111111101000000 (
b11010100100010010100000010101001 "
b11010100100010010100000010101001 &
b1010100100010010011111110111101 %
b1 #
b1 '
b100101 $
#38
b11111111111111111111111111100001 !
b11111111111111111111111111100001 (
b1101001111000011010010111010011 "
b1101001111000011010010111010011 &
b11101001111000011010001101011010 %
b10 #
b10 '
b100110 $
#39
b11111111111111111111111111100010 !
b11111111111111111111111111100010 (
b11100010010101010110001011000100 "
b11100010010101010110001011000100 &
b1100010010101010110000100010011 %
b11 #
b11 '
b100111 $
#40
b11111111111111111111111111101010 !
b11111111111111111111111111101010 (
b11110101010111111011010011101010 "
b11110101010111111011010011101010 &
b1110101010111111011001100111000 %
b0 #
b0 '
b101000 $
#41
b11111111111111111111111101011101 !
b11111111111111111111111101011101 (
b1100111101000101110100011001 "
b1100111101000101110100011001 &
b10001100111101000101101111011001 %
b1 #
b1 '
b101001 $
#42
b11111111111111111111111100110000 !
b11111111111111111111111100110000 (
b100100001100001001001101001000 "
b100100001100001001001101001000 &
b10100100001100001001000111000110 %
b10 #
b10 '
b101010 $
#43
b11111111111111111111111100000100 !
b11111111111111111111111100000100 (
b100000100011100101100001000 "
b100000100011100101100001000 &
b10000100000100011100100110001111 %
b11 #
b11 '
b101011 $
#44
b11111111111111111111111111100110 !
b11111111111111111111111111100110 (
b11110011000010011010110011100110 "
b11110011000010011010110011100110 &
b1110011000010011010101010000100 %
b0 #
b0 '
b101100 $
#45
b11111111111111111111111101000000 !
b11111111111111111111111101000000 (
b11000110111010100100000010001101 "
b11000110111010100100000010001101 &
b1000110111010100011111110110101 %
b1 #
b1 '
b101101 $
#46
b11111111111111111111111110000110 !
b11111111111111111111111110000110 (
b1101110100001100011011111011101 "
b1101110100001100011011111011101 &
b11101110100001100011010011110010 %
b10 #
b10 '
b101110 $
#47
b11111111111111111111111110000111 !
b11111111111111111111111110000111 (
b10000111000110101011000000001110 "
b10000111000110101011000000001110 &
b111000110101010111111001011 %
b11 #
b11 '
b101111 $
#48
b11111111111111111111111101110110 !
b11111111111111111111111101110110 (
b111011000101110001011101110110 "
b111011000101110001011101110110 &
b10111011000101110001010010010000 %
b0 #
b0 '
b110000 $
#49
b11111111111111111111111111001000 !
b11111111111111111111111111001000 (
b10010010000101101100100000100100 "
b10010010000101101100100000100100 &
b10010000101101100011101010001 %
b1 #
b1 '
b110001 $
#50
b11111111111111111111111110101101 !
b11111111111111111111111110101101 (
b11101011101011011011101011010111 "
b11101011101011011011101011010111 &
b1101011101011011011100011011110 %
b10 #
b10 '
b110010 $
#51
b11111111111111111111111101000101 !
b11111111111111111111111101000101 (
b1000101010111100101000110001010 "
b1000101010111100101000110001010 &
b11000101010111100100111111000111 %
b11 #
b11 '
b110011 $
#52
b11111111111111111111111101001100 !
b11111111111111111111111101001100 (
b10100110010110011111111001001100 "
b10100110010110011111111001001100 &
b100110010110011111110101011100 %
b0 #
b0 '
b110100 $
#53
b11111111111111111111111110010000 !
b11111111111111111111111110010000 (
b11000101010010011001000010001010 "
b11000101010010011001000010001010 &
b1000101010010011000111010101101 %
b1 #
b1 '
b110101 $
#54
b11111111111111111111111111010011 !
b11111111111111111111111111010011 (
b1000110110100110000101110001101 "
b1000110110100110000101110001101 &
b11000110110100110000100110001010 %
b10 #
b10 '
b110110 $
#55
b11111111111111111111111101111000 !
b11111111111111111111111101111000 (
b1111000000001001010011111110000 "
b1111000000001001010011111110000 &
b11111000000001001010010110000011 %
b11 #
b11 '
b110111 $
#56
b11111111111111111111111111111011 !
b11111111111111111111111111111011 (
b11111101101000110011001011111011 "
b11111101101000110011001011111011 &
b1111101101000110011000011101000 %
b0 #
b0 '
b111000 $
#57
b11111111111111111111111111110010 !
b11111111111111111111111111110010 (
b10010110000100011111001000101100 "
b10010110000100011111001000101100 &
b10110000100011111000111001001 %
b1 #
b1 '
b111001 $
#58
b11111111111111111111111101101110 !
b11111111111111111111111101101110 (
b111011011101101010100001110 "
b111011011101101010100001110 &
b10000111011011101101001011110110 %
b10 #
b10 '
b111010 $
#59
b11111111111111111111111101100111 !
b11111111111111111111111101100111 (
b1100111011010110110111111001110 "
b1100111011010110110111111001110 &
b11100111011010110110110011111111 %
b11 #
b11 '
b111011 $
#60
b11111111111111111111111101100101 !
b11111111111111111111111101100101 (
b10110010100011100011110001100101 "
b10110010100011100011110001100101 &
b110010100011100011101100110100 %
b0 #
b0 '
b111100 $
#61
b11111111111111111111111100001111 !
b11111111111111111111111100001111 (
b1110000000110110000111111100000 "
b1110000000110110000111111100000 &
b11110000000110110000110010100101 %
b1 #
b1 '
b111101 $
#62
b11111111111111111111111111110010 !
b11111111111111111111111111110010 (
b110001111100101000001101100011 "
b110001111100101000001101100011 &
b10110001111100101000000100100010 %
b10 #
b10 '
b111110 $
#63
b11111111111111111111111111010000 !
b11111111111111111111111111010000 (
b11010000111000100010010010100001 "
b11010000111000100010010010100001 &
b1010000111000100010001000111011 %
b11 #
b11 '
b111111 $
#64
b11111111111111111111111111000110 !
b11111111111111111111111111000110 (
b11100011000011010110101011000110 "
b11100011000011010110101011000110 &
b1100011000011010110100001000000 %
b0 #
b0 '
b1000000 $
#65
b11111111111111111111111110111100 !
b11111111111111111111111110111100 (
b11101000010001111011110011010000 "
b11101000010001111011110011010000 &
b1101000010001111011101101000001 %
b1 #
b1 '
b1000001 $
#66
b11111111111111111111111100110100 !
b11111111111111111111111100110100 (
b1100001001101000100001111000010 "
b1100001001101000100001111000010 &
b11100001001101000100000000001110 %
b10 #
b10 '
b1000010 $
#67
b11111111111111111111111110111110 !
b11111111111111111111111110111110 (
b10111110001001100000001001111100 "
b10111110001001100000001001111100 &
b111110001001100000000100110111 %
b11 #
b11 '
b1000011 $
#68
b11111111111111111111111101100111 !
b11111111111111111111111101100111 (
b110011101101011100011101100111 "
b110011101101011100011101100111 &
b10110011101101011100010000001100 %
b0 #
b0 '
b1000100 $
#69
b11111111111111111111111110011011 !
b11111111111111111111111110011011 (
b1100111100011101001101111001111 "
b1100111100011101001101111001111 &
b11100111100011101001100110011101 %
b1 #
b1 '
b1000101 $
#70
b11111111111111111111111110011010 !
b11111111111111111111111110011010 (
b11000100100110101111110010001001 "
b11000100100110101111110010001001 &
b1000100100110101111101110111010 %
b10 #
b10 '
b1000110 $
#71
b11111111111111111111111101001010 !
b11111111111111111111111101001010 (
b1001010100111100000011110010101 "
b1001010100111100000011110010101 &
b11001010100111100000010111110011 %
b11 #
b11 '
b1000111 $
#72
b11111111111111111111111110011001 !
b11111111111111111111111110011001 (
b11001100110010110001110010011001 "
b11001100110010110001110010011001 &
b1001100110010110001101010011000 %
b0 #
b0 '
b1001000 $
#73
b11111111111111111111111100000101 !
b11111111111111111111111100000101 (
b1101001100101100000010111010011 "
b1101001100101100000010111010011 &
b11101001100101100000001110111001 %
b1 #
b1 '
b1001001 $
#74
b11111111111111111111111100001010 !
b11111111111111111111111100001010 (
b101111000010100110001101011110 "
b101111000010100110001101011110 &
b10101111000010100110000000100110 %
b10 #
b10 '
b1001010 $
#75
b11111111111111111111111110010010 !
b11111111111111111111111110010010 (
b10010010010101101110111000100100 "
b10010010010101101110111000100100 &
b10010010101101110110001101111 %
b11 #
b11 '
b1001011 $
#76
b11111111111111111111111100001100 !
b11111111111111111111111100001100 (
b10000110000010111111100000001100 "
b10000110000010111111100000001100 &
b110000010111111011111100100 %
b0 #
b0 '
b1001100 $
#77
b11111111111111111111111100010110 !
b11111111111111111111111100010110 (
b11101011000100000001011011010110 "
b11101011000100000001011011010110 &
b1101011000100000001010110010101 %
b1 #
b1 '
b1001101 $
#78
b11111111111111111111111110001110 !
b11111111111111111111111110001110 (
b100010100011101101101101000101 "
b100010100011101101101101000101 &
b10100010100011101101100101010010 %
b10 #
b10 '
b1001110 $
#79
b11111111111111111111111111000110 !
b11111111111111111111111111000110 (
b11000110101111110011001010001101 "
b11000110101111110011001010001101 &
b1000110101111110011000010101011 %
b11 #
b11 '
b1001111 $
#80
b11111111111111111111111100011010 !
b11111111111111111111111100011010 (
b1101001111011010100100011010 "
b1101001111011010100100011010 &
b10001101001111011010011111110000 %
b0 #
b0 '
b1010000 $
#81
b11111111111111111111111110101101 !
b11111111111111111111111110101101 (
b1100011110101101010110111000111 "
b1100011110101101010110111000111 &
b11100011110101101010101100110001 %
b1 #
b1 '
b1010001 $
#82
b11111111111111111111111111001001 !
b11111111111111111111111111001001 (
b10000100110010011001010000001001 "
b10000100110010011001010000001001 &
b100110010011001001100111110 %
b10 #
b10 '
b1010010 $
#83
b11111111111111111111111100100101 !
b11111111111111111111111100100101 (
b100101001000110001000101001010 "
b100101001000110001000101001010 &
b10100101001000110000111010100111 %
b11 #
b11 '
b1010011 $
#84
b11111111111111111111111100100110 !
b11111111111111111111111100100110 (
b10010011011110000011100000100110 "
b10010011011110000011100000100110 &
b10011011110000011011010111100 %
b0 #
b0 '
b1010100 $
#85
b11111111111111111111111101100011 !
b11111111111111111111111101100011 (
b1101000110001110110001111010001 "
b1101000110001110110001111010001 &
b11101000110001110110000010001101 %
b1 #
b1 '
b1010101 $
#86
b11111111111111111111111100011100 !
b11111111111111111111111100011100 (
b1101000000111000111101111010000 "
b1101000000111000111101111010000 &
b11101000000111000111100111101010 %
b10 #
b10 '
b1010110 $
#87
b11111111111111111111111101001010 !
b11111111111111111111111101001010 (
b1001010111010001000010110010101 "
b1001010111010001000010110010101 &
b11001010111010001000001001100011 %
b11 #
b11 '
b1010111 $
#88
b11111111111111111111111110011010 !
b11111111111111111111111110011010 (
b1001101001100100111001110011010 "
b1001101001100100111001110011010 &
b11001101001100100111000001001000 %
b0 #
b0 '
b1011000 $
#89
b11111111111111111111111110010010 !
b11111111111111111111111110010010 (
b11010001010111111001001010100010 "
b11010001010111111001001010100010 &
b1010001010111111001000110101001 %
b1 #
b1 '
b1011001 $
#90
b11111111111111111111111110010110 !
b11111111111111111111111110010110 (
b10101100101100011101100101011 "
b10101100101100011101100101011 &
b10010101100101100011100101010110 %
b10 #
b10 '
b1011010 $
#91
b11111111111111111111111100100011 !
b11111111111111111111111100100011 (
b100011100010110100100101000111 "
b100011100010110100100101000111 &
b10100011100010110100011111011111 %
b11 #
b11 '
b1011011 $
#92
b11111111111111111111111110100010 !
b11111111111111111111111110100010 (
b11010001000011011110001010100010 "
b11010001000011011110001010100010 &
b1010001000011011110000010010100 %
b0 #
b0 '
b1011100 $
#93
b11111111111111111111111101011100 !
b11111111111111111111111101011100 (
b11111101000110000101110011111010 "
b11111101000110000101110011111010 &
b1111101000110000101101010000101 %
b1 #
b1 '
b1011101 $
#94
b11111111111111111111111110011110 !
b11111111111111111111111110011110 (
b1000011100111100011111110000111 "
b1000011100111100011111110000111 &
b11000011100111100011110110000010 %
b10 #
b10 '
b1011110 $
#95
b11111111111111111111111101101100 !
b11111111111111111111111101101100 (
b1101100010110001101110111011000 "
b1101100010110001101110111011000 &
b11101100010110001101101100011011 %
b11 #
b11 '
b1011111 $
#96
b11111111111111111111111101000010 !
b11111111111111111111111101000010 (
b100001011000101101010101000010 "
b100001011000101101010101000010 &
b10100001011000101101001110100000 %
b0 #
b0 '
b1100000 $
#97
b11111111111111111111111110011000 !
b11111111111111111111111110011000 (
b10010100100000101001100000101001 "
b10010100100000101001100000101001 &
b10100100000101001011100100001 %
b1 #
b1 '
b1100001 $
#98
b11111111111111111111111101100000 !
b11111111111111111111111101100000 (
b100101011000001011010101001010 "
b100101011000001011010101001010 &
b10100101011000001011001001101110 %
b10 #
b10 '
b1100010 $
#99
b11111111111111111111111110001001 !
b11111111111111111111111110001001 (
b10001001111011000111101000010011 "
b10001001111011000111101000010011 &
b1001111011000111100000010111 %
b11 #
b11 '
b1100011 $
#100
b11111111111111111111111111011001 !
b11111111111111111111111111011001 (
b11101100100011000101011011011001 "
b11101100100011000101011011011001 &
b1101100100011000101010101101100 %
b0 #
b0 '
b1100100 $
#101
b11111111111111111111111111100100 !
b11111111111111111111111111100100 (
b11100010001000101110010011000100 "
b11100010001000101110010011000100 &
b1100010001000101110001101111101 %
b1 #
b1 '
b1100101 $
#102
b11111111111111111111111111111010 !
b11111111111111111111111111111010 (
b10111110111110101000011001111101 "
b10111110111110101000011001111101 &
b111110111110101000010000011010 %
b10 #
b10 '
b1100110 $
#103
b11111111111111111111111100101011 !
b11111111111111111111111100101011 (
b101011011010110001110101010110 "
b101011011010110001110101010110 &
b10101011011010110001101011010011 %
b11 #
b11 '
b1100111 $
#104
b11111111111111111111111110011111 !
b11111111111111111111111110011111 (
b1001111111101000011001110011111 "
b1001111111101000011001110011111 &
b11001111111101000011000111111000 %
b0 #
b0 '
b1101000 $
#105
b11111111111111111111111110011100 !
b11111111111111111111111110011100 (
b10011111000011011001110000111110 "
b10011111000011011001110000111110 &
b11111000011011001101110011001 %
b1 #
b1 '
b1101001 $
#106
b11111111111111111111111101100101 !
b11111111111111111111111101100101 (
b10101010011001010110000001010100 "
b10101010011001010110000001010100 &
b101010011001010101111010000110 %
b10 #
b10 '
b1101010 $
#107
b11111111111111111111111111110111 !
b11111111111111111111111111110111 (
b11110111011111111000000011101110 "
b11110111011111111000000011101110 &
b1110111011111110111111101001111 %
b11 #
b11 '
b1101011 $
#108
b11111111111111111111111101010011 !
b11111111111111111111111101010011 (
b101001110111101111011101010011 "
b101001110111101111011101010011 &
b10101001110111101111010101000100 %
b0 #
b0 '
b1101100 $
#109
b11111111111111111111111111011100 !
b11111111111111111111111111011100 (
b11001111010000101101110010011110 "
b11001111010000101101110010011110 &
b1001111010000101101101101110101 %
b1 #
b1 '
b1101101 $
#110
b11111111111111111111111100100011 !
b11111111111111111111111100100011 (
b111001001000111010111101110010 "
b111001001000111010111101110010 &
b10111001001000111010110110110010 %
b10 #
b10 '
b1101110 $
#111
b11111111111111111111111100111111 !
b11111111111111111111111100111111 (
b111111000101100010001101111110 "
b111111000101100010001101111110 &
b10111111000101100010000110001011 %
b11 #
b11 '
b1101111 $
#112
b11111111111111111111111110001011 !
b11111111111111111111111110001011 (
b11000101111101111110110010001011 "
b11000101111101111110110010001011 &
b1000101111101111110101101010000 %
b0 #
b0 '
b1110000 $
#113
b11111111111111111111111110000001 !
b11111111111111111111111110000001 (
b1001110010101000000100010011 "
b1001110010101000000100010011 &
b10001001110010100111111100010001 %
b1 #
b1 '
b1110001 $
#114
b11111111111111111111111110101100 !
b11111111111111111111111110101100 (
b10011110101011001001111000111101 "
b10011110101011001001111000111101 &
b11110101011001001110110011110 %
b10 #
b10 '
b1110010 $
#115
b11111111111111111111111101110001 !
b11111111111111111111111101110001 (
b1110001110110010011111111100011 "
b1110001110110010011111111100011 &
b11110001110110010011110110000111 %
b11 #
b11 '
b1110011 $
#116
b11111111111111111111111111100001 !
b11111111111111111111111111100001 (
b1110000100111010010001111100001 "
b1110000100111010010001111100001 &
b11110000100111010010000000011100 %
b0 #
b0 '
b1110100 $
#117
b11111111111111111111111100100101 !
b11111111111111111111111100100101 (
b1001000100100000010010110010001 "
b1001000100100000010010110010001 &
b11001000100100000010001001101101 %
b1 #
b1 '
b1110101 $
#118
b11111111111111111111111110011000 !
b11111111111111111111111110011000 (
b10001111100110000001110000011111 "
b10001111100110000001110000011111 &
b1111100110000001101001001010 %
b10 #
b10 '
b1110110 $
#119
b11111111111111111111111111010000 !
b11111111111111111111111111010000 (
b11010000011011001101000010100000 "
b11010000011011001101000010100000 &
b1010000011011001100111101000011 %
b11 #
b11 '
b1110111 $
#120
b11111111111111111111111101111001 !
b11111111111111111111111101111001 (
b111100111010110110000101111001 "
b111100111010110110000101111001 &
b10111100111010110101111110101000 %
b0 #
b0 '
b1111000 $
#121
b11111111111111111111111100100011 !
b11111111111111111111111100100011 (
b11011111111110010001100110111 "
b11011111111110010001100110111 &
b10011011111111110010000110001001 %
b1 #
b1 '
b1111001 $
#122
b11111111111111111111111110001010 !
b11111111111111111111111110001010 (
b10000001100010101101000000000011 "
b10000001100010101101000000000011 &
b1100010101100111110110110 %
b10 #
b10 '
b1111010 $
#123
b11111111111111111111111110011000 !
b11111111111111111111111110011000 (
b10011000011010101001010000110000 "
b10011000011010101001010000110000 &
b11000011010101001001010111111 %
b11 #
b11 '
b1111011 $
#124
b11111111111111111111111100010011 !
b11111111111111111111111100010011 (
b1001100010100011011100010011 "
b1001100010100011011100010011 &
b10001001100010100011010111110100 %
b0 #
b0 '
b1111100 $
#125
b11111111111111111111111110011010 !
b11111111111111111111111110011010 (
b11011110010111101001101010111100 "
b11011110010111101001101010111100 &
b1011110010111101001100001100101 %
b1 #
b1 '
b1111101 $
#126
b11111111111111111111111111100010 !
b11111111111111111111111111100010 (
b1110111111000100010101111101111 "
b1110111111000100010101111101111 &
b11110111111000100010100111100010 %
b10 #
b10 '
b1111110 $
#127
b11111111111111111111111110100110 !
b11111111111111111111111110100110 (
b10100110000111100000010001001100 "
b10100110000111100000010001001100 &
b100110000111100000001111111011 %
b11 #
b11 '
b1111111 $
#128
b11111111111111111111111100100000 !
b11111111111111111111111100100000 (
b10010000001101111111000000100000 "
b10010000001101111111000000100000 &
b10000001101111110111100000000 %
b0 #
b0 '
b10000000 $
#129
b11111111111111111111111101100101 !
b11111111111111111111111101100101 (
b1000010111011010110010110000101 "
b1000010111011010110010110000101 &
b11000010111011010110001100000001 %
b1 #
b1 '
b10000001 $
#130
b11111111111111111111111100100000 !
b11111111111111111111111100100000 (
b1001001000000101011100010010 "
b1001001000000101011100010010 &
b10001001001000000101010011001110 %
b10 #
b10 '
b10000010 $
#131
b11111111111111111111111101001000 !
b11111111111111111111111101001000 (
b1001000000000000110000110010000 "
b1001000000000000110000110010000 &
b11001000000000000101111011110111 %
b11 #
b11 '
b10000011 $
#132
b11111111111111111111111100011000 !
b11111111111111111111111100011000 (
b1100000101011001100100011000 "
b1100000101011001100100011000 &
b10001100000101011001011011001100 %
b0 #
b0 '
b10000100 $
#133
b11111111111111111111111100011111 !
b11111111111111111111111100011111 (
b1011100101111100001111110111001 "
b1011100101111100001111110111001 &
b11011100101111100001110101011101 %
b1 #
b1 '
b10000101 $
#134
b11111111111111111111111100011000 !
b11111111111111111111111100011000 (
b1001000110000011111100010010 "
b1001000110000011111100010010 &
b10001001000110000011110001111010 %
b10 #
b10 '
b10000110 $
#135
b11111111111111111111111110111111 !
b11111111111111111111111110111111 (
b10111111111101001010000001111111 "
b10111111111101001010000001111111 &
b111111111101001001111110110011 %
b11 #
b11 '
b10000111 $
#136
b11111111111111111111111110000101 !
b11111111111111111111111110000101 (
b11000010101100101111101010000101 "
b11000010101100101111101010000101 &
b1000010101100101111100101011000 %
b0 #
b0 '
b10001000 $
#137
b11111111111111111111111100100100 !
b11111111111111111111111100100100 (
b11111001010100110010010011110010 "
b11111001010100110010010011110010 &
b1111001010100110010001101111001 %
b1 #
b1 '
b10001001 $
#138
b11111111111111111111111111011001 !
b11111111111111111111111111011001 (
b11110110011000111100000111 "
b11110110011000111100000111 &
b10000011110110011000110011100110 %
b10 #
b10 '
b10001010 $
#139
b11111111111111111111111110101110 !
b11111111111111111111111110101110 (
b10101110010000111000010001011100 "
b10101110010000111000010001011100 &
b101110010000111000001000101111 %
b11 #
b11 '
b10001011 $
#140
b11111111111111111111111111110111 !
b11111111111111111111111111110111 (
b1111011110110101010010111110111 "
b1111011110110101010010111110111 &
b11111011110110101010001010100100 %
b0 #
b0 '
b10001100 $
#141
b11111111111111111111111110010010 !
b11111111111111111111111110010010 (
b11101010111110101001001011010101 "
b11101010111110101001001011010101 &
b1101010111110101001000101010101 %
b1 #
b1 '
b10001101 $
#142
b11111111111111111111111101011100 !
b11111111111111111111111101011100 (
b1110101010111001011010111101010 "
b1110101010111001011010111101010 &
b11110101010111001011001000010010 %
b10 #
b10 '
b10001110 $
#143
b11111111111111111111111101100010 !
b11111111111111111111111101100010 (
b1100010010101111000010111000100 "
b1100010010101111000010111000100 &
b11100010010101111000001001101011 %
b11 #
b11 '
b10001111 $
#144
b11111111111111111111111101101000 !
b11111111111111111111111101101000 (
b10110100000111011110000001101000 "
b10110100000111011110000001101000 &
b110100000111011101111010110000 %
b0 #
b0 '
b10010000 $
#145
b11111111111111111111111101000100 !
b11111111111111111111111101000100 (
b10011110111010100100010000111101 "
b10011110111010100100010000111101 &
b11110111010100100001011110001 %
b1 #
b1 '
b10010001 $
#146
b11111111111111111111111111101110 !
b11111111111111111111111111101110 (
b1101001111011101101100111010011 "
b1101001111011101101100111010011 &
b11101001111011101101011111111110 %
b10 #
b10 '
b10010010 $
#147
b11111111111111111111111111001101 !
b11111111111111111111111111001101 (
b11001101001110001101111010011010 "
b11001101001110001101111010011010 &
b1001101001110001101110001100111 %
b11 #
b11 '
b10010011 $
#148
b11111111111111111111111100101100 !
b11111111111111111111111100101100 (
b10110001000001011101100101100 "
b10110001000001011101100101100 &
b10010110001000001011100101111100 %
b0 #
b0 '
b10010100 $
#149
b11111111111111111111111111010111 !
b11111111111111111111111111010111 (
b11011000110111101011100110110 "
b11011000110111101011100110110 &
b10011011000110111101010001001101 %
b1 #
b1 '
b10010101 $
#150
b11111111111111111111111101011101 !
b11111111111111111111111101011101 (
b11110011010111011110110011100110 "
b11110011010111011110110011100110 &
b1110011010111011110101010101010 %
b10 #
b10 '
b10010110 $
